Workbook

Sheet LSA data
A1: MCID | B1: CID | C1: Campaign Name | D1: AID | E1: MAID | F1: Advertiser Name | G1: BID | H1: Business | I1: Budget | J1: Start Date | K1: Last 7 Days | L1: Last 30 Days | M1: Service Principal Name | N1: Service Principal Manager | O1: Channel | P1: Google ID | Q1: Notes | R1: MCC | S1: Google Spend
A2: 924-255-5564 | B2: 4377259 | C2: LSA | Brown, Harris and Faulkner | Synthetic | D2: 984335 | E2: 226522 | F2: Mayer LLC | G2: 5673 | H2: Mayer LLC INC | I2: 12453.06 | J2: 46143 | K2: 2746.98 | L2: 65392.16 | M2: Empower Global Relationships | N2: Lynn Houston | O2: National | P2: =VLOOKUP($B2,'Report 2'!$A:$U,15,FALSE) | R2: =VLOOKUP($P2,'MCC data'!$C:$S,3,FALSE) | S2: =VLOOKUP($P2,'MCC data'!$C:$S,13,FALSE)
A3: 699-229-2012 | B3: 1213024 | C3: LSA | Brown, Harris and Faulkner | Synthetic | D3: 984335 | E3: 226522 | F3: Adams, Warner and Gibson | G3: 5673 | H3: Adams, Warner and Gibson INC | I3: 26633.16 | J3: 46099 | K3: 7198.85 | L3: 35341.09 | M3: Empower Global Relationships | N3: Lynn Houston | O3: National | P3: =VLOOKUP($B3,'Report 2'!$A:$U,15,FALSE) | R3: =VLOOKUP($P3,'MCC data'!$C:$S,3,FALSE) | S3: =VLOOKUP($P3,'MCC data'!$C:$S,13,FALSE)
A4: 924-255-5564 | B4: 0279207 | C4: LSA | King, Moore and Anderson | Synthetic | D4: 090391 | E4: 923608 | F4: Simmons-Keller | G4: 5673 | H4: Simmons-Keller INC | I4: 16154.28 | J4: 46143 | K4: 5816.38 | L4: 38168.49 | M4: Empower Global Relationships | N4: Lynn Houston | O4: National | P4: =VLOOKUP($B4,'Report 2'!$A:$U,15,FALSE) | R4: =VLOOKUP($P4,'MCC data'!$C:$S,3,FALSE) | S4: =VLOOKUP($P4,'MCC data'!$C:$S,13,FALSE)
A5: 699-229-2012 | B5: 0014103 | C5: LSA | Adkins, Garner and Ferrell | Synthetic | D5: 201405 | E5: 767346 | F5: Williams, Dudley and Williams | G5: 5673 | H5: Williams, Dudley and Williams INC | I5: 38736.59 | J5: 46080 | K5: 364.78 | L5: 49180.9 | M5: Empower Global Relationships | N5: Lynn Houston | O5: National | P5: =VLOOKUP($B5,'Report 2'!$A:$U,15,FALSE) | R5: =VLOOKUP($P5,'MCC data'!$C:$S,3,FALSE) | S5: =VLOOKUP($P5,'MCC data'!$C:$S,13,FALSE)
A6: 485-905-1145 | B6: 4763391 | C6: LSA | Adkins, Garner and Ferrell | Synthetic | D6: 201405 | E6: 767346 | F6: Morrison-Wood | G6: 5673 | H6: Morrison-Wood INC | I6: 31814.91 | J6: 46127 | K6: 10041.99 | L6: 55246.04 | M6: Empower Global Relationships | N6: Lynn Houston | O6: National | P6: =VLOOKUP($B6,'Report 2'!$A:$U,15,FALSE) | R6: =VLOOKUP($P6,'MCC data'!$C:$S,3,FALSE) | S6: =VLOOKUP($P6,'MCC data'!$C:$S,13,FALSE)
A7: 485-905-1145 | B7: 8016035 | C7: LSA | Neal Inc | Synthetic | D7: 682991 | E7: 797949 | F7: Jones, Taylor and Washington | G7: 5673 | H7: Jones, Taylor and Washington INC | I7: 36176.39 | J7: 46119 | K7: 0 | L7: 20485.58 | M7: Empower Global Relationships | N7: Lynn Houston | O7: National | P7: =VLOOKUP($B7,'Report 2'!$A:$U,15,FALSE) | Q7: Ad is paused | R7: =VLOOKUP($P7,'MCC data'!$C:$S,3,FALSE) | S7: =VLOOKUP($P7,'MCC data'!$C:$S,13,FALSE)
A8: 924-255-5564 | B8: 7403920 | C8: LSA | Neal Inc | Synthetic | D8: 682991 | E8: 797949 | F8: Benson and Sons | G8: 5673 | H8: Benson and Sons INC | I8: 6967.42 | J8: 46143 | K8: 6564.03 | L8: 67884.99 | M8: Empower Global Relationships | N8: Lynn Houston | O8: National | P8: =VLOOKUP($B8,'Report 2'!$A:$U,15,FALSE) | R8: =VLOOKUP($P8,'MCC data'!$C:$S,3,FALSE) | S8: =VLOOKUP($P8,'MCC data'!$C:$S,13,FALSE)
A9: 924-255-5564 | B9: 6741168 | C9: LSA | Solis-Newton | Synthetic | D9: 743566 | E9: 140570 | F9: Hunter-Maddox | G9: 5673 | H9: Hunter-Maddox INC | I9: 33947.36 | J9: 46143 | K9: 13436.92 | L9: 47082.89 | M9: Empower Global Relationships | N9: Lynn Houston | O9: National | P9: =VLOOKUP($B9,'Report 2'!$A:$U,15,FALSE) | R9: =VLOOKUP($P9,'MCC data'!$C:$S,3,FALSE) | S9: =VLOOKUP($P9,'MCC data'!$C:$S,13,FALSE)
A10: 924-255-5564 | B10: 9639972 | C10: LSA | Jensen Ltd | Synthetic | D10: 484845 | E10: 833866 | F10: Martinez Inc | G10: 5673 | H10: Martinez Inc INC | I10: 32335.37 | J10: 46143 | K10: 0 | L10: 105.58 | M10: Empower Global Relationships | N10: Lynn Houston | O10: National | P10: =VLOOKUP($B10,'Report 2'!$A:$U,15,FALSE) | Q10: Ad is paused | R10: =VLOOKUP($P10,'MCC data'!$C:$S,3,FALSE) | S10: =VLOOKUP($P10,'MCC data'!$C:$S,13,FALSE)
A11: 699-229-2012 | B11: 6045981 | C11: LSA | Munoz Inc | Synthetic | D11: 329844 | E11: 714582 | F11: Ramirez LLC | G11: 5673 | H11: Ramirez LLC INC | I11: 48885.03 | J11: 46028 | K11: 8296.66 | L11: 41339.57 | M11: Empower Global Relationships | N11: Lynn Houston | O11: National | P11: =VLOOKUP($B11,'Report 2'!$A:$U,15,FALSE) | R11: =VLOOKUP($P11,'MCC data'!$C:$S,3,FALSE) | S11: =VLOOKUP($P11,'MCC data'!$C:$S,13,FALSE)
A12: 699-229-2012 | B12: 3841770 | C12: LSA | Munoz Inc | Synthetic | D12: 329844 | E12: 714582 | F12: Hubbard-Lee | G12: 5673 | H12: Hubbard-Lee INC | I12: 6388.44 | J12: 46053 | K12: 0 | L12: 61070.73 | M12: Empower Global Relationships | N12: Lynn Houston | O12: National | P12: =VLOOKUP($B12,'Report 2'!$A:$U,15,FALSE) | Q12: - | R12: =VLOOKUP($P12,'MCC data'!$C:$S,3,FALSE) | S12: =VLOOKUP($P12,'MCC data'!$C:$S,13,FALSE)
A13: 699-229-2012 | B13: 1410320 | C13: LSA | Cox, Thornton and Stout | Synthetic | D13: 907675 | E13: 631921 | F13: King-Ellis | G13: 5673 | H13: King-Ellis INC | I13: 44260.23 | J13: 45964 | K13: 0 | L13: 0 | M13: Empower Global Relationships | N13: Lynn Houston | O13: National | P13: =VLOOKUP($B13,'Report 2'!$A:$U,15,FALSE) | Q13: Red(License) Blue(Background check) | R13: =VLOOKUP($P13,'MCC data'!$C:$S,3,FALSE) | S13: =VLOOKUP($P13,'MCC data'!$C:$S,13,FALSE)
A14: 699-229-2012 | B14: 0770993 | C14: LSA | Erickson-Patrick | Synthetic | D14: 266805 | E14: 290959 | F14: Wyatt Group | G14: 5673 | H14: Wyatt Group INC | I14: 20508.05 | J14: 46028 | K14: 0 | L14: 0 | M14: Empower Global Relationships | N14: Lynn Houston | O14: National | P14: =VLOOKUP($B14,'Report 2'!$A:$U,15,FALSE) | Q14: Red(Business Profile) | R14: =VLOOKUP($P14,'MCC data'!$C:$S,3,FALSE) | S14: =VLOOKUP($P14,'MCC data'!$C:$S,13,FALSE)
A15: 699-229-2012 | B15: 3355597 | C15: LSA | Erickson-Patrick | Synthetic | D15: 266805 | E15: 290959 | F15: Keller Group | G15: 5673 | H15: Keller Group INC | I15: 54528.13 | J15: 46064 | K15: 0 | L15: 22183.73 | M15: Empower Global Relationships | N15: Lynn Houston | O15: National | P15: =VLOOKUP($B15,'Report 2'!$A:$U,15,FALSE) | Q15: Ad is paused | R15: =VLOOKUP($P15,'MCC data'!$C:$S,3,FALSE) | S15: =VLOOKUP($P15,'MCC data'!$C:$S,13,FALSE)
A16: 699-229-2012 | B16: 8612737 | C16: LSA | Erickson-Patrick | Synthetic | D16: 266805 | E16: 290959 | F16: Caldwell, Hernandez and Wilkinson | G16: 5673 | H16: Caldwell, Hernandez and Wilkinson INC | I16: 4346.49 | J16: 45911 | K16: 0 | L16: 32017.82 | M16: Empower Global Relationships | N16: Lynn Houston | O16: National | P16: =VLOOKUP($B16,'Report 2'!$A:$U,15,FALSE) | Q16: - | R16: =VLOOKUP($P16,'MCC data'!$C:$S,3,FALSE) | S16: =VLOOKUP($P16,'MCC data'!$C:$S,13,FALSE)
A17: 924-255-5564 | B17: 2958661 | C17: LSA | Ferrell-Wright | Synthetic | D17: 405947 | E17: 570928 | F17: Clarke, Davis and Gilbert | G17: 5673 | H17: Clarke, Davis and Gilbert INC | I17: 10421.23 | J17: 46143 | K17: 6437.41 | L17: 44997.48 | M17: Empower Global Relationships | N17: Lynn Houston | O17: National | P17: =VLOOKUP($B17,'Report 2'!$A:$U,15,FALSE) | R17: =VLOOKUP($P17,'MCC data'!$C:$S,3,FALSE) | S17: =VLOOKUP($P17,'MCC data'!$C:$S,13,FALSE)
A18: 699-229-2012 | B18: 4587014 | C18: LSA | Ferrell-Wright | Synthetic | D18: 405947 | E18: 570928 | F18: Bryant-Park | G18: 5673 | H18: Bryant-Park INC | I18: 18291.99 | J18: 46029 | K18: 0 | L18: 0 | M18: Empower Global Relationships | N18: Lynn Houston | O18: National | P18: =VLOOKUP($B18,'Report 2'!$A:$U,15,FALSE) | Q18: Ad is paused | R18: =VLOOKUP($P18,'MCC data'!$C:$S,3,FALSE) | S18: =VLOOKUP($P18,'MCC data'!$C:$S,13,FALSE)
A19: 924-255-5564 | B19: 4312088 | C19: LSA | Bell, Vargas and West | Synthetic | D19: 072086 | E19: 897556 | F19: Edwards-Jefferson | G19: 5673 | H19: Edwards-Jefferson INC | I19: 48660.34 | J19: 46143 | K19: 4762.03 | L19: 37508.5 | M19: Empower Global Relationships | N19: Lynn Houston | O19: National | P19: =VLOOKUP($B19,'Report 2'!$A:$U,15,FALSE) | R19: =VLOOKUP($P19,'MCC data'!$C:$S,3,FALSE) | S19: =VLOOKUP($P19,'MCC data'!$C:$S,13,FALSE)
A20: 699-229-2012 | B20: 0619718 | C20: LSA | Bell, Vargas and West | Synthetic | D20: 072086 | E20: 897556 | F20: Bishop Inc | G20: 5673 | H20: Bishop Inc INC | I20: 45236.62 | J20: 46099 | K20: 4064.56 | L20: 33096.79 | M20: Empower Global Relationships | N20: Lynn Houston | O20: National | P20: =VLOOKUP($B20,'Report 2'!$A:$U,15,FALSE) | R20: =VLOOKUP($P20,'MCC data'!$C:$S,3,FALSE) | S20: =VLOOKUP($P20,'MCC data'!$C:$S,13,FALSE)
A21: 699-229-2012 | B21: 9118017 | C21: LSA | Warren-Cook | Synthetic | D21: 683035 | E21: 237834 | F21: Jacobson-Alvarez | G21: 5673 | H21: Jacobson-Alvarez INC | I21: 57572.07 | J21: 46036 | K21: 0 | L21: 37334.89 | M21: Empower Global Relationships | N21: Lynn Houston | O21: National | P21: =VLOOKUP($B21,'Report 2'!$A:$U,15,FALSE) | Q21: Ad is paused | R21: =VLOOKUP($P21,'MCC data'!$C:$S,3,FALSE) | S21: =VLOOKUP($P21,'MCC data'!$C:$S,13,FALSE)
A22: 485-905-1145 | B22: 5441663 | C22: LSA | Smith-Hawkins | Synthetic | D22: 339277 | E22: 149790 | F22: Moore Ltd | G22: 0377 | H22: Moore Ltd INC | I22: 25845.05 | J22: 46121 | K22: 11950.03 | L22: 43020.57 | M22: Re-Intermediate Extensible Schemas | N22: Stephen Vargas | O22: DirectLocal | P22: =VLOOKUP($B22,'Report 2'!$A:$U,15,FALSE) | R22: =VLOOKUP($P22,'MCC data'!$C:$S,3,FALSE) | S22: =VLOOKUP($P22,'MCC data'!$C:$S,13,FALSE)
A23: 699-229-2012 | B23: 2717907 | C23: LSA | Valdez, Stout and Martin | Synthetic | D23: 435153 | E23: 415143 | F23: Rivera-Bauer | G23: 5673 | H23: Rivera-Bauer INC | I23: 3693.4 | J23: 45964 | K23: 0 | L23: 0 | M23: Empower Global Relationships | N23: Lynn Houston | O23: National | P23: =VLOOKUP($B23,'Report 2'!$A:$U,15,FALSE) | Q23: Ad is paused | R23: =VLOOKUP($P23,'MCC data'!$C:$S,3,FALSE) | S23: =VLOOKUP($P23,'MCC data'!$C:$S,13,FALSE)
A24: 924-255-5564 | B24: 8243520 | C24: LSA | Rodriguez and Sons | Synthetic | D24: 823403 | E24: 966939 | F24: Powell-Patterson | G24: 5673 | H24: Powell-Patterson INC | I24: 25940.49 | J24: 46143 | K24: 9095.21 | L24: 42346.21 | M24: Empower Global Relationships | N24: Lynn Houston | O24: National | P24: =VLOOKUP($B24,'Report 2'!$A:$U,15,FALSE) | R24: =VLOOKUP($P24,'MCC data'!$C:$S,3,FALSE) | S24: =VLOOKUP($P24,'MCC data'!$C:$S,13,FALSE)
A25: 699-229-2012 | B25: 1880662 | C25: LSA | Jensen Ltd | Synthetic | D25: 484845 | E25: 833866 | F25: Palmer-Boyd | G25: 5673 | H25: Palmer-Boyd INC | I25: 13748.26 | J25: 46028 | K25: 0 | L25: 0 | M25: Empower Global Relationships | N25: Lynn Houston | O25: National | P25: =VLOOKUP($B25,'Report 2'!$A:$U,15,FALSE) | Q25: Red(Insurance & Business Profile) | R25: =VLOOKUP($P25,'MCC data'!$C:$S,3,FALSE) | S25: =VLOOKUP($P25,'MCC data'!$C:$S,13,FALSE)
A26: 924-255-5564 | B26: 8014053 | C26: LSA | Hunt, Ray and Smith | Synthetic | D26: 050570 | E26: 848332 | F26: Shelton, Gamble and Irwin | G26: 5673 | H26: Shelton, Gamble and Irwin INC | I26: 43743.81 | J26: 46143 | K26: 0 | L26: 20484.45 | M26: Empower Global Relationships | N26: Lynn Houston | O26: National | P26: =VLOOKUP($B26,'Report 2'!$A:$U,15,FALSE) | Q26: Yellow(Billing & Background check) | R26: =VLOOKUP($P26,'MCC data'!$C:$S,3,FALSE) | S26: =VLOOKUP($P26,'MCC data'!$C:$S,13,FALSE)
A27: 924-255-5564 | B27: 6619964 | C27: LSA | Patel Inc | Synthetic | D27: 710174 | E27: 527784 | F27: Garcia-Fernandez | G27: 5673 | H27: Garcia-Fernandez INC | I27: 52398.11 | J27: 46143 | K27: 771.52 | L27: 33889.66 | M27: Empower Global Relationships | N27: Lynn Houston | O27: National | P27: =VLOOKUP($B27,'Report 2'!$A:$U,15,FALSE) | R27: =VLOOKUP($P27,'MCC data'!$C:$S,3,FALSE) | S27: =VLOOKUP($P27,'MCC data'!$C:$S,13,FALSE)
A28: 485-905-1145 | B28: 6640961 | C28: LSA | Reyes, Olson and Morgan | Synthetic | D28: 339129 | E28: 558898 | F28: Hernandez, Vang and Reynolds | G28: 8295 | H28: Hernandez, Vang and Reynolds INC | I28: 52743.45 | J28: 46144 | K28: 12230.24 | L28: 16917.32 | M28: E-Enable B2C Experiences | N28: Angela Cole | O28: National | P28: =VLOOKUP($B28,'Report 2'!$A:$U,15,FALSE) | R28: =VLOOKUP($P28,'MCC data'!$C:$S,3,FALSE) | S28: =VLOOKUP($P28,'MCC data'!$C:$S,13,FALSE)
A29: 924-255-5564 | B29: 1750840 | C29: LSA | Paul-Jackson | Synthetic | D29: 168585 | E29: 238338 | F29: Davis, Wright and Stewart | G29: 8295 | H29: Davis, Wright and Stewart INC | I29: 17956.57 | J29: 46142 | K29: 5351.1 | L29: 14548.02 | M29: E-Enable B2C Experiences | N29: Angela Cole | O29: National | P29: =VLOOKUP($B29,'Report 2'!$A:$U,15,FALSE) | R29: =VLOOKUP($P29,'MCC data'!$C:$S,3,FALSE) | S29: =VLOOKUP($P29,'MCC data'!$C:$S,13,FALSE)
A30: 924-255-5564 | B30: 5304145 | C30: LSA | White, Walker and Boyd | Synthetic | D30: 627311 | E30: 597914 | F30: Butler-Mitchell | G30: 5673 | H30: Butler-Mitchell INC | I30: 58538.43 | J30: 46143 | K30: 1959.4 | L30: 24375.49 | M30: Empower Global Relationships | N30: Lynn Houston | O30: National | P30: =VLOOKUP($B30,'Report 2'!$A:$U,15,FALSE) | R30: =VLOOKUP($P30,'MCC data'!$C:$S,3,FALSE) | S30: =VLOOKUP($P30,'MCC data'!$C:$S,13,FALSE)
A31: 924-255-5564 | B31: 9969654 | C31: LSA | Winters, Nelson and Nichols | Synthetic | D31: 656687 | E31: 321065 | F31: Shepard, Harris and Lewis | G31: 2138 | H31: Shepard, Harris and Lewis INC | I31: 45302.53 | J31: 46128 | K31: 6871.28 | L31: 14796.41 | M31: E-Enable B2C Experiences | N31: Angela Cole | O31: National | P31: =VLOOKUP($B31,'Report 2'!$A:$U,15,FALSE) | R31: =VLOOKUP($P31,'MCC data'!$C:$S,3,FALSE) | S31: =VLOOKUP($P31,'MCC data'!$C:$S,13,FALSE)
A32: 485-905-1145 | B32: 0877130 | C32: LSA | Bell-Cook | Synthetic | D32: 166721 | E32: 394590 | F32: Peterson-Gonzalez | G32: 8295 | H32: Peterson-Gonzalez INC | I32: 9627.88 | J32: 46121 | K32: 121.53 | L32: 24248.96 | M32: E-Enable B2C Experiences | N32: Angela Cole | O32: National | P32: =VLOOKUP($B32,'Report 2'!$A:$U,15,FALSE) | R32: =VLOOKUP($P32,'MCC data'!$C:$S,3,FALSE) | S32: =VLOOKUP($P32,'MCC data'!$C:$S,13,FALSE)
A33: 699-229-2012 | B33: 0350002 | C33: LSA | Patterson and Sons | Synthetic | D33: 310234 | E33: 105479 | F33: Foster-Haynes | G33: 8295 | H33: Foster-Haynes INC | I33: 48953.89 | J33: 45619 | K33: 0 | L33: 0 | M33: E-Enable B2C Experiences | N33: Angela Cole | O33: National | P33: =VLOOKUP($B33,'Report 2'!$A:$U,15,FALSE) | Q33: Ad is paused | R33: =VLOOKUP($P33,'MCC data'!$C:$S,3,FALSE) | S33: =VLOOKUP($P33,'MCC data'!$C:$S,13,FALSE)
A34: 924-255-5564 | B34: 6748855 | C34: LSA | Harris and Sons | Synthetic | D34: 268276 | E34: 170580 | F34: Long and Sons | G34: 5673 | H34: Long and Sons INC | I34: 45890.48 | J34: 46143 | K34: 10528.38 | L34: 5565.9 | M34: Empower Global Relationships | N34: Lynn Houston | O34: National | P34: =VLOOKUP($B34,'Report 2'!$A:$U,15,FALSE) | R34: =VLOOKUP($P34,'MCC data'!$C:$S,3,FALSE) | S34: =VLOOKUP($P34,'MCC data'!$C:$S,13,FALSE)
A35: 699-229-2012 | B35: 5805491 | C35: LSA | Hampton-Carrillo | Synthetic | D35: 560065 | E35: 273859 | F35: Richardson-Lee | G35: 5673 | H35: Richardson-Lee INC | I35: 16845.97 | J35: 46038 | K35: 0 | L35: 44571.18 | M35: Empower Global Relationships | N35: Lynn Houston | O35: National | P35: =VLOOKUP($B35,'Report 2'!$A:$U,15,FALSE) | Q35: Red(Insurance & License & Business Profile) | R35: =VLOOKUP($P35,'MCC data'!$C:$S,3,FALSE) | S35: =VLOOKUP($P35,'MCC data'!$C:$S,13,FALSE)
A36: 699-229-2012 | B36: 9679852 | C36: LSA | Hampton-Carrillo | Synthetic | D36: 560065 | E36: 273859 | F36: Murray, Hunter and Stephenson | G36: 5673 | H36: Murray, Hunter and Stephenson INC | I36: 50843.57 | J36: 46028 | K36: 0 | L36: 0 | M36: Empower Global Relationships | N36: Lynn Houston | O36: National | P36: =VLOOKUP($B36,'Report 2'!$A:$U,15,FALSE) | Q36: Red(License) Blue(Business Profile) | R36: =VLOOKUP($P36,'MCC data'!$C:$S,3,FALSE) | S36: =VLOOKUP($P36,'MCC data'!$C:$S,13,FALSE)
A37: 924-255-5564 | B37: 6037777 | C37: LSA | Clark-Merritt | Synthetic | D37: 358165 | E37: 534760 | F37: Wyatt and Sons | G37: 8295 | H37: Wyatt and Sons INC | I37: 30524.1 | J37: 46144 | K37: 10736.95 | L37: 18456.5 | M37: Grow Plug-And-Play Functionalities | N37: Gina Sullivan | O37: National | P37: =VLOOKUP($B37,'Report 2'!$A:$U,15,FALSE) | R37: =VLOOKUP($P37,'MCC data'!$C:$S,3,FALSE) | S37: =VLOOKUP($P37,'MCC data'!$C:$S,13,FALSE)
A38: 485-905-1145 | B38: 9848964 | C38: LSA | Norris-Caldwell | Synthetic | D38: 673726 | E38: 711011 | F38: Daniel-Neal | G38: 8295 | H38: Daniel-Neal INC | I38: 26035.5 | J38: 46116 | K38: 10176.32 | L38: 45544.61 | M38: Revolutionize B2C Platforms | N38: Jason Drake | O38: National | P38: =VLOOKUP($B38,'Report 2'!$A:$U,15,FALSE) | R38: =VLOOKUP($P38,'MCC data'!$C:$S,3,FALSE) | S38: =VLOOKUP($P38,'MCC data'!$C:$S,13,FALSE)
A39: 924-255-5564 | B39: 0551698 | C39: LSA | Bernard-Bell | Synthetic | D39: 372339 | E39: 786774 | F39: Collins and Sons | G39: 9932 | H39: Collins and Sons INC | I39: 50386.73 | J39: 46144 | K39: 8994.38 | L39: 65610.8 | M39: E-Enable B2C Experiences | N39: Angela Cole | O39: National | P39: =VLOOKUP($B39,'Report 2'!$A:$U,15,FALSE) | R39: =VLOOKUP($P39,'MCC data'!$C:$S,3,FALSE) | S39: =VLOOKUP($P39,'MCC data'!$C:$S,13,FALSE)
A40: 699-229-2012 | B40: 4575678 | C40: LSA | Taylor-Miller | Synthetic | D40: 032019 | E40: 339773 | F40: Gray and Sons | G40: 8295 | H40: Gray and Sons INC | I40: 19429.69 | J40: 45276 | K40: 0 | L40: 0 | M40: Grow Plug-And-Play Functionalities | N40: Gina Sullivan | O40: National | P40: =VLOOKUP($B40,'Report 2'!$A:$U,15,FALSE) | Q40: Red(License) | R40: =VLOOKUP($P40,'MCC data'!$C:$S,3,FALSE) | S40: =VLOOKUP($P40,'MCC data'!$C:$S,13,FALSE)
A41: 485-905-1145 | B41: 7287466 | C41: LSA | Reed-Rivera | Synthetic | D41: 123821 | E41: 151395 | F41: Greene-Potter | G41: 7819 | H41: Greene-Potter INC | I41: 50135.54 | J41: 46117 | K41: 8235.57 | L41: 63353.85 | M41: E-Enable B2C Experiences | N41: Angela Cole | O41: National | P41: =VLOOKUP($B41,'Report 2'!$A:$U,15,FALSE) | R41: =VLOOKUP($P41,'MCC data'!$C:$S,3,FALSE) | S41: =VLOOKUP($P41,'MCC data'!$C:$S,13,FALSE)
A42: 924-255-5564 | B42: 2076209 | C42: LSA | Martin, Wilson and Carr | Synthetic | D42: 052240 | E42: 557218 | F42: Alvarado LLC | G42: 8295 | H42: Alvarado LLC INC | I42: 24235.3 | J42: 46148 | K42: 0 | L42: 45130.68 | M42: E-Enable B2C Experiences | N42: Angela Cole | O42: National | P42: =VLOOKUP($B42,'Report 2'!$A:$U,15,FALSE) | Q42: - | R42: =VLOOKUP($P42,'MCC data'!$C:$S,3,FALSE) | S42: =VLOOKUP($P42,'MCC data'!$C:$S,13,FALSE)
A43: 699-229-2012 | B43: 3560156 | C43: LSA | Rose-Chan | Synthetic | D43: 344344 | E43: 464198 | F43: Moody-Brennan | G43: 5037 | H43: Moody-Brennan INC | I43: 39933.51 | J43: 45492 | K43: 0 | L43: 0 | M43: Incentivize Holistic E-Business | N43: Peggy Patrick | O43: DummyG | P43: =VLOOKUP($B43,'Report 2'!$A:$U,15,FALSE) | Q43: Red(License & Billing) Blue(Background check) | R43: =VLOOKUP($P43,'MCC data'!$C:$S,3,FALSE) | S43: =VLOOKUP($P43,'MCC data'!$C:$S,13,FALSE)
A44: 924-255-5564 | B44: 0174706 | C44: LSA | Stevens-Lee | Synthetic | D44: 002170 | E44: 978981 | F44: Clark-Henry | G44: 5673 | H44: Clark-Henry INC | I44: 11010.32 | J44: 46143 | K44: 0 | L44: 59152.62 | M44: Empower Global Relationships | N44: Lynn Houston | O44: National | P44: =VLOOKUP($B44,'Report 2'!$A:$U,15,FALSE) | Q44: Ad is paused | R44: =VLOOKUP($P44,'MCC data'!$C:$S,3,FALSE) | S44: =VLOOKUP($P44,'MCC data'!$C:$S,13,FALSE)
A45: 485-905-1145 | B45: 7010530 | C45: LSA | Sullivan Inc | Synthetic | D45: 986937 | E45: 300109 | F45: Guzman LLC | G45: 5673 | H45: Guzman LLC INC | I45: 24171.27 | J45: 46112 | K45: 0 | L45: 15600.17 | M45: Empower Global Relationships | N45: Lynn Houston | O45: National | P45: =VLOOKUP($B45,'Report 2'!$A:$U,15,FALSE) | Q45: - | R45: =VLOOKUP($P45,'MCC data'!$C:$S,3,FALSE) | S45: =VLOOKUP($P45,'MCC data'!$C:$S,13,FALSE)
A46: 485-905-1145 | B46: 2812117 | C46: LSA | Sullivan Inc | Synthetic | D46: 986937 | E46: 300109 | F46: Moreno and Sons | G46: 5673 | H46: Moreno and Sons INC | I46: 16604.5 | J46: 46123 | K46: 2838.74 | L46: 61418.79 | M46: Empower Global Relationships | N46: Lynn Houston | O46: National | P46: =VLOOKUP($B46,'Report 2'!$A:$U,15,FALSE) | R46: =VLOOKUP($P46,'MCC data'!$C:$S,3,FALSE) | S46: =VLOOKUP($P46,'MCC data'!$C:$S,13,FALSE)
A47: 924-255-5564 | B47: 0808785 | C47: LSA | Williams-Williams | Synthetic | D47: 767639 | E47: 349240 | F47: Pugh LLC | G47: 5673 | H47: Pugh LLC INC | I47: 44045.07 | J47: 46143 | K47: 7756.88 | L47: 27873.67 | M47: Empower Global Relationships | N47: Lynn Houston | O47: National | P47: =VLOOKUP($B47,'Report 2'!$A:$U,15,FALSE) | R47: =VLOOKUP($P47,'MCC data'!$C:$S,3,FALSE) | S47: =VLOOKUP($P47,'MCC data'!$C:$S,13,FALSE)
A48: 699-229-2012 | B48: 6464066 | C48: LSA | Williams-Williams | Synthetic | D48: 767639 | E48: 349240 | F48: Anderson-Peters | G48: 5673 | H48: Anderson-Peters INC | I48: 1372.27 | J48: 46028 | K48: 0 | L48: 14863.79 | M48: Empower Global Relationships | N48: Lynn Houston | O48: National | P48: =VLOOKUP($B48,'Report 2'!$A:$U,15,FALSE) | Q48: Ad is paused | R48: =VLOOKUP($P48,'MCC data'!$C:$S,3,FALSE) | S48: =VLOOKUP($P48,'MCC data'!$C:$S,13,FALSE)
A49: 699-229-2012 | B49: 2548593 | C49: LSA | Kelley PLC | Synthetic | D49: 936164 | E49: 221953 | F49: Christensen PLC | G49: 5673 | H49: Christensen PLC INC | I49: 36747.21 | J49: 46052 | K49: 3195.61 | L49: 4129.1 | M49: Empower Global Relationships | N49: Lynn Houston | O49: National | P49: =VLOOKUP($B49,'Report 2'!$A:$U,15,FALSE) | R49: =VLOOKUP($P49,'MCC data'!$C:$S,3,FALSE) | S49: =VLOOKUP($P49,'MCC data'!$C:$S,13,FALSE)
A50: 699-229-2012 | B50: 0892225 | C50: LSA | Morgan-Grant | Synthetic | D50: 725448 | E50: 541462 | F50: Barr-Washington | G50: 8295 | H50: Barr-Washington INC | I50: 2937.46 | J50: 44786 | K50: 0 | L50: 0 | M50: Revolutionize B2C Platforms | N50: Jason Drake | O50: National | P50: =VLOOKUP($B50,'Report 2'!$A:$U,15,FALSE) | Q50: Ad is paused | R50: =VLOOKUP($P50,'MCC data'!$C:$S,3,FALSE) | S50: =VLOOKUP($P50,'MCC data'!$C:$S,13,FALSE)
A51: 699-229-2012 | B51: 7659420 | C51: LSA | Lozano-Hill | Synthetic | D51: 825582 | E51: 515294 | F51: Brooks, Brown and Duran | G51: 5673 | H51: Brooks, Brown and Duran INC | I51: 56689.65 | J51: 46052 | K51: 8479.34 | L51: 43345.42 | M51: Empower Global Relationships | N51: Lynn Houston | O51: National | P51: =VLOOKUP($B51,'Report 2'!$A:$U,15,FALSE) | R51: =VLOOKUP($P51,'MCC data'!$C:$S,3,FALSE) | S51: =VLOOKUP($P51,'MCC data'!$C:$S,13,FALSE)
A52: 699-229-2012 | B52: 0904045 | C52: LSA | Johnson, Spears and Gray | Synthetic | D52: 886370 | E52: 292942 | F52: Sanford LLC | G52: 2916 | H52: Sanford LLC INC | I52: 21613.47 | J52: 46091 | K52: 0 | L52: 64097.39 | M52: Innovate Cross-Media Content | N52: System | O52: Partner | P52: =VLOOKUP($B52,'Report 2'!$A:$U,15,FALSE) | Q52: - | R52: =VLOOKUP($P52,'MCC data'!$C:$S,3,FALSE) | S52: =VLOOKUP($P52,'MCC data'!$C:$S,13,FALSE)
A53: 485-905-1145 | B53: 3603537 | C53: LSA | Johnson, Spears and Gray | Synthetic | D53: 886370 | E53: 292942 | F53: Santos PLC | G53: 2916 | H53: Santos PLC INC | I53: 36093.89 | J53: 46105 | K53: 0 | L53: 0 | M53: Innovate Cross-Media Content | N53: System | O53: Partner | P53: =VLOOKUP($B53,'Report 2'!$A:$U,15,FALSE) | Q53: Ad is paused | R53: =VLOOKUP($P53,'MCC data'!$C:$S,3,FALSE) | S53: =VLOOKUP($P53,'MCC data'!$C:$S,13,FALSE)
A54: 924-255-5564 | B54: 9213593 | C54: LSA | Wood Inc | Synthetic | D54: 487292 | E54: 186612 | F54: Cameron, Thompson and Nelson | G54: 8295 | H54: Cameron, Thompson and Nelson INC | I54: 2505.8 | J54: 46134 | K54: 8445.14 | L54: 27737.1 | M54: E-Enable B2C Experiences | N54: Angela Cole | O54: National | P54: =VLOOKUP($B54,'Report 2'!$A:$U,15,FALSE) | R54: =VLOOKUP($P54,'MCC data'!$C:$S,3,FALSE) | S54: =VLOOKUP($P54,'MCC data'!$C:$S,13,FALSE)
A55: 485-905-1145 | B55: 2816188 | C55: LSA | Smith, Gardner and Jones | Synthetic | D55: 349044 | E55: 990981 | F55: Banks Ltd | G55: 5673 | H55: Banks Ltd INC | I55: 26148.49 | J55: 46124 | K55: 12856.54 | L55: 66989.01 | M55: Empower Global Relationships | N55: Lynn Houston | O55: National | P55: =VLOOKUP($B55,'Report 2'!$A:$U,15,FALSE) | R55: =VLOOKUP($P55,'MCC data'!$C:$S,3,FALSE) | S55: =VLOOKUP($P55,'MCC data'!$C:$S,13,FALSE)
A56: 924-255-5564 | B56: 2940332 | C56: LSA | Reese PLC | Synthetic | D56: 783887 | E56: 666010 | F56: Powell-Patterson | G56: 5673 | H56: Powell-Patterson INC | I56: 44954.95 | J56: 46143 | K56: 4447.75 | L56: 37901.51 | M56: Empower Global Relationships | N56: Lynn Houston | O56: National | P56: =VLOOKUP($B56,'Report 2'!$A:$U,15,FALSE) | R56: =VLOOKUP($P56,'MCC data'!$C:$S,3,FALSE) | S56: =VLOOKUP($P56,'MCC data'!$C:$S,13,FALSE)
A57: 485-905-1145 | B57: 7090538 | C57: LSA | Reese PLC | Synthetic | D57: 783887 | E57: 666010 | F57: Wiley, Gray and Graham | G57: 5673 | H57: Wiley, Gray and Graham INC | I57: 44050.5 | J57: 46112 | K57: 8179.15 | L57: 36367.7 | M57: Empower Global Relationships | N57: Lynn Houston | O57: National | P57: =VLOOKUP($B57,'Report 2'!$A:$U,15,FALSE) | R57: =VLOOKUP($P57,'MCC data'!$C:$S,3,FALSE) | S57: =VLOOKUP($P57,'MCC data'!$C:$S,13,FALSE)
A58: 924-255-5564 | B58: 9232111 | C58: LSA | Rubio and Sons | Synthetic | D58: 619951 | E58: 926160 | F58: Cunningham-Klein | G58: 5673 | H58: Cunningham-Klein INC | I58: 38005.75 | J58: 46143 | K58: 10518.13 | L58: 50625.88 | M58: Empower Global Relationships | N58: Lynn Houston | O58: National | P58: =VLOOKUP($B58,'Report 2'!$A:$U,15,FALSE) | R58: =VLOOKUP($P58,'MCC data'!$C:$S,3,FALSE) | S58: =VLOOKUP($P58,'MCC data'!$C:$S,13,FALSE)
A59: 699-229-2012 | B59: 1293303 | C59: LSA | Rubio and Sons | Synthetic | D59: 619951 | E59: 926160 | F59: Rogers PLC | G59: 5673 | H59: Rogers PLC INC | I59: 27997.04 | J59: 46075 | K59: 9827.69 | L59: 50365.03 | M59: Empower Global Relationships | N59: Lynn Houston | O59: National | P59: =VLOOKUP($B59,'Report 2'!$A:$U,15,FALSE) | R59: =VLOOKUP($P59,'MCC data'!$C:$S,3,FALSE) | S59: =VLOOKUP($P59,'MCC data'!$C:$S,13,FALSE)
A60: 924-255-5564 | B60: 3558130 | C60: LSA | Cuevas-Bell | Synthetic | D60: 740769 | E60: 792393 | F60: Murray-Miller | G60: 5673 | H60: Murray-Miller INC | I60: 15198.6 | J60: 46143 | K60: 3344.93 | L60: 22344.32 | M60: Empower Global Relationships | N60: Lynn Houston | O60: National | P60: =VLOOKUP($B60,'Report 2'!$A:$U,15,FALSE) | R60: =VLOOKUP($P60,'MCC data'!$C:$S,3,FALSE) | S60: =VLOOKUP($P60,'MCC data'!$C:$S,13,FALSE)
A61: 699-229-2012 | B61: 8997981 | C61: LSA | Reed, Weaver and Jones | Synthetic | D61: 824099 | E61: 586085 | F61: Jones, Brown and Herrera | G61: 5673 | H61: Jones, Brown and Herrera INC | I61: 23384.88 | J61: 46028 | K61: 0 | L61: 69001.47 | M61: Empower Global Relationships | N61: Lynn Houston | O61: National | P61: =VLOOKUP($B61,'Report 2'!$A:$U,15,FALSE) | R61: =VLOOKUP($P61,'MCC data'!$C:$S,3,FALSE) | S61: =VLOOKUP($P61,'MCC data'!$C:$S,13,FALSE)
A62: 699-229-2012 | B62: 0391400 | C62: LSA | Reynolds, Fletcher and Cook | Synthetic | D62: 495574 | E62: 449289 | F62: Ramirez-Robertson | G62: 5673 | H62: Ramirez-Robertson INC | I62: 56266.43 | J62: 46028 | K62: 7521.21 | L62: 39767.79 | M62: Empower Global Relationships | N62: Lynn Houston | O62: National | P62: =VLOOKUP($B62,'Report 2'!$A:$U,15,FALSE) | R62: =VLOOKUP($P62,'MCC data'!$C:$S,3,FALSE) | S62: =VLOOKUP($P62,'MCC data'!$C:$S,13,FALSE)
A63: 699-229-2012 | B63: 8822764 | C63: LSA | Reynolds, Fletcher and Cook | Synthetic | D63: 495574 | E63: 449289 | F63: Gray-Monroe | G63: 5673 | H63: Gray-Monroe INC | I63: 56588.5 | J63: 46008 | K63: 0 | L63: 20976.07 | M63: Empower Global Relationships | N63: Lynn Houston | O63: National | P63: =VLOOKUP($B63,'Report 2'!$A:$U,15,FALSE) | R63: =VLOOKUP($P63,'MCC data'!$C:$S,3,FALSE) | S63: =VLOOKUP($P63,'MCC data'!$C:$S,13,FALSE)
A64: 699-229-2012 | B64: 3084154 | C64: LSA | Hill, Scott and Barnett | Synthetic | D64: 218760 | E64: 680394 | F64: Camacho, Taylor and Hoover | G64: 5673 | H64: Camacho, Taylor and Hoover INC | I64: 23502.1 | J64: 45964 | K64: 0 | L64: 37619.55 | M64: Empower Global Relationships | N64: Lynn Houston | O64: National | P64: =VLOOKUP($B64,'Report 2'!$A:$U,15,FALSE) | R64: =VLOOKUP($P64,'MCC data'!$C:$S,3,FALSE) | S64: =VLOOKUP($P64,'MCC data'!$C:$S,13,FALSE)
A65: 924-255-5564 | B65: 0649194 | C65: LSA | Olson and Sons | Synthetic | D65: 315058 | E65: 908526 | F65: Silva, Pena and Dennis | G65: 5673 | H65: Silva, Pena and Dennis INC | I65: 56588.29 | J65: 46143 | K65: 2977.15 | L65: 64068.67 | M65: Empower Global Relationships | N65: Lynn Houston | O65: National | P65: =VLOOKUP($B65,'Report 2'!$A:$U,15,FALSE) | R65: =VLOOKUP($P65,'MCC data'!$C:$S,3,FALSE) | S65: =VLOOKUP($P65,'MCC data'!$C:$S,13,FALSE)
... A583: 801-048-2685 | B583: 3691955 | C583: LSA | Moore, Turner and Osborne | Synthetic | D583: 822980 | E583: 444465 | F583: Swanson Inc | G583: 5673 | H583: Swanson Inc INC | I583: 6860.08 | J583: 46146 | K583: 7953.7 | L583: 66429.13 | M583: Empower Global Relationships | N583: Lynn Houston | O583: National | P583: =VLOOKUP($B583,'Report 2'!$A:$U,15,FALSE) | R583: =VLOOKUP($P583,'MCC data'!$C:$S,3,FALSE) | S583: =VLOOKUP($P583,'MCC data'!$C:$S,13,FALSE)
P1220: g

Sheet Report 2
A1: CID | B1: Mcid | C1: AID | D1: Maid | E1: BID | F1: Business Name | G1: Budget | H1: Spent | I1: Start | J1: Campaign Created | K1: Paid | L1: Status | M1: AR Status | N1: Channel | O1: Client ID | P1: Offer ID | Q1: Payment Method | R1: Contract Length | S1: Offer Name | T1: Wpc Status | U1: Wpc End Date
A2: 1662148 | B2: 801-048-2685 | C2: 842242 | D2: 042324 | E2: 0746 | F2: Anderson, Summers and Jones | G2: 43633.2 | H2: 0 | I2: 46149 | J2: 46149.484 | K2: 46149.484 | M2: pending | N2: National | O2: 5916500764 | P2: 2303 | Q2: Credit Card | S2: Local Services Ads | T2: running
A3: 7726344 | B3: 801-048-2685 | C3: 349391 | D3: 784017 | E3: 3698 | F3: Thomas and Sons | G3: 83942.15 | H3: 0 | I3: 46150 | J3: 46149.436 | K3: 46149.446 | M3: pending | N3: National | O3: 1492400035 | P3: 2303 | Q3: Credit Card | S3: Local Services Ads | T3: running
A4: 3360119 | B4: 801-048-2685 | C4: 815707 | D4: 465221 | E4: 2816 | F4: Martin, Brown and Frank | G4: 29147.87 | H4: 0 | I4: 46150 | J4: 46149.351 | K4: 46149.352 | M4: pending | N4: DummyG | O4: 2249967510 | P4: 2101 | Q4: Invoice | S4: XMO | T4: running
A5: 3394343 | B5: 801-048-2685 | C5: 396446 | D5: 844265 | E5: 9588 | F5: Hanson, Hall and Case | G5: 24269.33 | H5: 0 | I5: 46149 | J5: 46149.246 | K5: 46149.246 | M5: pending | N5: National | O5: 5370965818 | P5: 1948 | Q5: Credit Card | S5: Local Services Ads | T5: running
A6: 3394343 | B6: 801-048-2685 | C6: 396446 | D6: 844265 | E6: 9588 | F6: Hanson, Hall and Case | G6: 73202.22 | H6: 0 | I6: 46149 | J6: 46149.246 | K6: 46149.246 | M6: pending | N6: National | O6: 5370965818 | P6: 1948 | Q6: Credit Card | S6: Local Services Ads | T6: ended | U6: 45092
A7: 4620908 | B7: 801-048-2685 | C7: 927241 | D7: 172484 | E7: 7521 | F7: Coleman, Brown and Brown | G7: 76437.09 | H7: 0 | I7: 46149 | J7: 46149.218 | K7: 46149.34 | M7: pending | N7: Local | O7: 8598321515 | P7: 2303 | Q7: Invoice | S7: Local Services Ads | T7: running
A8: 7329087 | B8: 801-048-2685 | C8: 927241 | D8: 172484 | E8: 7521 | F8: Hansen, Murphy and Robinson | G8: 35614.74 | H8: 0 | I8: 46149 | J8: 46149.205 | K8: 46149.34 | M8: pending | N8: Local | O8: 1833846387 | P8: 2303 | Q8: Invoice | S8: Local Services Ads | T8: running
A9: 7884442 | B9: 801-048-2685 | C9: 927241 | D9: 172484 | E9: 7521 | F9: Moore, Dawson and Alvarez | G9: 77330.88 | H9: 0 | I9: 46149 | J9: 46149.205 | K9: 46149.34 | M9: pending | N9: Local | O9: 8182903864 | P9: 2303 | Q9: Invoice | S9: Local Services Ads | T9: running
A10: 9787583 | B10: 801-048-2685 | C10: 927241 | D10: 172484 | E10: 7521 | F10: Reyes and Sons | G10: 85429.92 | H10: 0 | I10: 46149 | J10: 46149.205 | K10: 46149.34 | M10: pending | N10: Local | O10: 1843625072 | P10: 2303 | Q10: Invoice | S10: Local Services Ads | T10: running
A11: 5451195 | B11: 801-048-2685 | C11: 927241 | D11: 172484 | E11: 7521 | F11: Hernandez Group | G11: 98126.69 | H11: 0 | I11: 46149 | J11: 46149.205 | K11: 46149.34 | M11: pending | N11: Local | O11: 4203318384 | P11: 2303 | Q11: Invoice | S11: Local Services Ads | T11: running
A12: 6078827 | B12: 801-048-2685 | C12: 927241 | D12: 172484 | E12: 7521 | F12: Morgan, Leach and Jackson | G12: 66602.16 | H12: 0 | I12: 46149 | J12: 46149.204 | K12: 46149.34 | M12: pending | N12: Local | O12: 1776944144 | P12: 2303 | Q12: Invoice | S12: Local Services Ads | T12: running
A13: 0388036 | B13: 801-048-2685 | C13: 927241 | D13: 172484 | E13: 7521 | F13: Serrano-Harrison | G13: 99044.66 | H13: 0 | I13: 46149 | J13: 46149.204 | K13: 46149.34 | M13: pending | N13: Local | O13: 1726373069 | P13: 2303 | Q13: Invoice | S13: Local Services Ads | T13: running
A14: 9369838 | B14: 801-048-2685 | C14: 927241 | D14: 172484 | E14: 7521 | F14: Perez-Perkins | G14: 23813.82 | H14: 0 | I14: 46149 | J14: 46149.204 | K14: 46149.34 | M14: pending | N14: Local | O14: 1642669667 | P14: 2303 | Q14: Invoice | S14: Local Services Ads | T14: running
A15: 3147158 | B15: 801-048-2685 | C15: 893795 | D15: 117515 | E15: 9980 | F15: Bell and Sons | G15: 14805.74 | H15: 0 | I15: 46149 | J15: 46148.679 | K15: 46148.721 | M15: pending | N15: National | O15: 9272488948 | P15: 2303 | Q15: Credit Card | S15: Local Services Ads | T15: running
A16: 0727548 | B16: 801-048-2685 | C16: 395149 | D16: 475343 | E16: 8295 | F16: Perez PLC | G16: 87300.97 | H16: 49437.58 | I16: 46148 | J16: 46148.485 | K16: 46148.485 | M16: pending | N16: National | O16: 8604361768 | P16: 2303 | Q16: Credit Card | S16: Local Services Ads | T16: running
A17: 7426122 | B17: 801-048-2685 | C17: 143001 | D17: 128223 | E17: 8295 | F17: Walton-White | G17: 69148.21 | H17: 46961.26 | I17: 46148 | J17: 46148.485 | K17: 46148.485 | M17: pending | N17: National | O17: 6090633975 | P17: 2303 | Q17: Credit Card | S17: Local Services Ads | T17: running
A18: 6872937 | B18: 801-048-2685 | C18: 202103 | D18: 093295 | E18: 1192 | F18: Riley-Allen | G18: 85649.8 | H18: 0 | I18: 46149 | J18: 46148.485 | K18: 46148.485 | M18: pending | N18: National | O18: 8880158481 | P18: 2303 | Q18: Credit Card | S18: Local Services Ads | T18: running
... A26: 7989742 | B26: 801-048-2685 | C26: 822980 | D26: 444465 | E26: 5673 | F26: Schneider PLC | G26: 25915.1 | H26: 47379.85 | I26: 46147 | J26: 46147.558 | K26: 46147.561 | M26: pending | N26: National | O26: 0690984218 | P26: 1948 | Q26: Invoice | S26: Local Services Ads | T26: running
A27: 7989742 | B27: 801-048-2685 | C27: 822980 | D27: 444465 | E27: 5673 | F27: Schneider PLC | G27: 22282.27 | H27: 7490.39 | I27: 46147 | J27: 46147.558 | K27: 46147.561 | M27: pending | N27: National | O27: 0690984218 | P27: 1948 | Q27: Invoice | S27: Local Services Ads | T27: ended | U27: 45100
A28: 6113154 | B28: 801-048-2685 | C28: 581185 | D28: 006574 | E28: 1192 | F28: Tucker-Wilson | G28: 70760.93 | H28: 40500.86 | I28: 46147 | J28: 46147.483 | K28: 46147.483 | M28: pending | N28: National | O28: 0051367125 | P28: 1948 | Q28: Credit Card | S28: Local Services Ads | T28: running
A29: 6113154 | B29: 801-048-2685 | C29: 581185 | D29: 006574 | E29: 1192 | F29: Tucker-Wilson | G29: 46532.99 | H29: 23362.13 | I29: 46147 | J29: 46147.483 | K29: 46147.483 | M29: pending | N29: National | O29: 0051367125 | P29: 1948 | Q29: Credit Card | S29: Local Services Ads | T29: ended | U29: 45097
A30: 8151652 | B30: 801-048-2685 | C30: 636979 | D30: 118442 | E30: 8295 | F30: Steele PLC | G30: 50392.77 | H30: 59313.19 | I30: 46148 | J30: 46147.482 | K30: 46147.482 | M30: pending | N30: National | O30: 8498634123 | P30: 2303 | Q30: Credit Card | S30: Local Services Ads | T30: running
A31: 8095112 | B31: 801-048-2685 | C31: 921951 | D31: 702707 | E31: 9142 | F31: Clarke PLC | G31: 226.99 | H31: 31239.43 | I31: 46148 | J31: 46147.482 | K31: 46147.572 | M31: pending | N31: Local | O31: 3277829980 | P31: 2303 | Q31: Credit Card | S31: Local Services Ads | T31: running
A32: 8233002 | B32: 801-048-2685 | C32: 024693 | D32: 773341 | E32: 1192 | F32: Hunt PLC | G32: 58025.74 | H32: 18261.89 | I32: 46147 | J32: 46147.482 | K32: 46147.482 | M32: pending | N32: National | O32: 3940476622 | P32: 1948 | Q32: Credit Card | S32: Local Services Ads | T32: running
A33: 8233002 | B33: 801-048-2685 | C33: 024693 | D33: 773341 | E33: 1192 | F33: Hunt PLC | G33: 22064.01 | H33: 49936.36 | I33: 46147 | J33: 46147.482 | K33: 46147.482 | M33: pending | N33: National | O33: 3940476622 | P33: 1948 | Q33: Credit Card | S33: Local Services Ads | T33: ended | U33: 45097
A34: 4792336 | B34: 801-048-2685 | C34: 591675 | D34: 799997 | E34: 1192 | F34: Jones Group | G34: 75000.23 | H34: 56685.9 | I34: 46148 | J34: 46147.482 | K34: 46147.482 | M34: pending | N34: National | O34: 7774057945 | P34: 1948 | Q34: Credit Card | S34: Local Services Ads | T34: ended | U34: 45107
A35: 4792336 | B35: 801-048-2685 | C35: 591675 | D35: 799997 | E35: 1192 | F35: Jones Group | G35: 50974.18 | H35: 3409 | I35: 46148 | J35: 46147.482 | K35: 46147.482 | M35: pending | N35: National | O35: 7774057945 | P35: 1948 | Q35: Credit Card | S35: Local Services Ads | T35: running
A36: 2009716 | B36: 801-048-2685 | C36: 456223 | D36: 517127 | E36: 1192 | F36: Johnson-Mckenzie | G36: 614.04 | H36: 18817.4 | I36: 46147 | J36: 46147.482 | K36: 46147.482 | M36: pending | N36: National | O36: 8318921616 | P36: 2303 | Q36: Credit Card | S36: Local Services Ads | T36: running
A37: 9155643 | B37: 801-048-2685 | C37: 379585 | D37: 681012 | E37: 1192 | F37: Browning, Brown and Pearson | G37: 81725.82 | H37: 46281.57 | I37: 46148 | J37: 46147.482 | K37: 46147.482 | M37: pending | N37: National | O37: 6833184923 | P37: 1948 | Q37: Credit Card | S37: Local Services Ads | T37: running
A38: 9155643 | B38: 801-048-2685 | C38: 379585 | D38: 681012 | E38: 1192 | F38: Browning, Brown and Pearson | G38: 8342.22 | H38: 969.06 | I38: 46148 | J38: 46147.482 | K38: 46147.482 | M38: pending | N38: National | O38: 6833184923 | P38: 1948 | Q38: Credit Card | S38: Local Services Ads | T38: ended | U38: 45098
A39: 6576293 | B39: 801-048-2685 | C39: 356393 | D39: 310835 | E39: 4744 | F39: Hughes, Blair and Gates | G39: 96364.99 | H39: 0 | I39: 46149 | J39: 46147.482 | K39: 46147.482 | M39: pending | N39: National | O39: 2261405045 | P39: 2303 | Q39: Credit Card | S39: Local Services Ads | T39: running
A40: 0838262 | B40: 801-048-2685 | C40: 222228 | D40: 551471 | E40: 6938 | F40: Ramos and Sons | G40: 34723.26 | H40: 28125.18 | I40: 46148 | J40: 46147.482 | K40: 46147.482 | M40: pending | N40: Local | O40: 1057098735 | P40: 2303 | Q40: Credit Card | S40: Local Services Ads | T40: running
A41: 0748354 | B41: 801-048-2685 | C41: 927754 | D41: 826006 | E41: 8295 | F41: Kelley, Smith and Roberson | G41: 92710.46 | H41: 57829.07 | I41: 46148 | J41: 46147.482 | K41: 46147.482 | M41: pending | N41: National | O41: 1270695837 | P41: 1948 | Q41: Credit Card | S41: Local Services Ads | T41: running
A42: 0748354 | B42: 801-048-2685 | C42: 927754 | D42: 826006 | E42: 8295 | F42: Kelley, Smith and Roberson | G42: 9978.87 | H42: 12860.86 | I42: 46148 | J42: 46147.482 | K42: 46147.482 | M42: pending | N42: National | O42: 1270695837 | P42: 1948 | Q42: Credit Card | S42: Local Services Ads | T42: ended | U42: 45092
A43: 5633097 | B43: 801-048-2685 | C43: 885782 | D43: 663601 | E43: 8295 | F43: Lopez-Vasquez | G43: 92632.91 | H43: 31868 | I43: 46147 | J43: 46147.482 | K43: 46147.482 | M43: pending | N43: National | O43: 5550975527 | P43: 2303 | Q43: Credit Card | S43: Local Services Ads | T43: running
A44: 4677946 | B44: 801-048-2685 | C44: 924322 | D44: 623669 | E44: 8295 | F44: Russell, Patel and Cox | G44: 70124.78 | H44: 10598.71 | I44: 46147 | J44: 46147.482 | K44: 46147.482 | M44: pending | N44: National | O44: 1667099462 | P44: 2303 | Q44: Credit Card | S44: Local Services Ads | T44: running
A45: 7688948 | B45: 801-048-2685 | C45: 831255 | D45: 996914 | E45: 9365 | F45: Vazquez PLC | G45: 85316.1 | H45: 0 | I45: 46148 | J45: 46147.482 | K45: 46147.482 | M45: pending | N45: National | O45: 8284447121 | P45: 2303 | Q45: Credit Card | S45: Local Services Ads | T45: running
A46: 8590918 | B46: 801-048-2685 | C46: 049473 | D46: 669031 | E46: 9365 | F46: Santiago Inc | G46: 26482.21 | H46: 0 | I46: 46149 | J46: 46147.481 | K46: 46147.482 | M46: pending | N46: National | O46: 6834399267 | P46: 2303 | Q46: Credit Card | S46: Local Services Ads | T46: running
A47: 1351106 | B47: 801-048-2685 | C47: 466202 | D47: 505141 | E47: 8295 | F47: Barrera Inc | G47: 94905.65 | H47: 27317.83 | I47: 46147 | J47: 46147.481 | K47: 46147.481 | M47: pending | N47: National | O47: 0866982738 | P47: 1948 | Q47: Credit Card | S47: Local Services Ads | T47: ended | U47: 45092
A48: 1351106 | B48: 801-048-2685 | C48: 466202 | D48: 505141 | E48: 8295 | F48: Barrera Inc | G48: 53527.63 | H48: 20126.57 | I48: 46147 | J48: 46147.481 | K48: 46147.481 | M48: pending | N48: National | O48: 0866982738 | P48: 1948 | Q48: Credit Card | S48: Local Services Ads | T48: running
A49: 7401599 | B49: 801-048-2685 | C49: 430691 | D49: 186058 | E49: 3375 | F49: Petersen LLC | G49: 96343.29 | H49: 36293.58 | I49: 46147 | J49: 46147.368 | K49: 46147.378 | M49: pending | N49: Local | O49: 5234973813 | P49: 2303 | Q49: Invoice | S49: Local Services Ads | T49: running
A50: 5974733 | B50: 801-048-2685 | C50: 430691 | D50: 186058 | E50: 3375 | F50: Carpenter-Mccullough | G50: 7006.46 | H50: 23294.27 | I50: 46147 | J50: 46147.368 | K50: 46147.378 | M50: pending | N50: Local | O50: 1746575984 | P50: 2303 | Q50: Invoice | S50: Local Services Ads | T50: running
A51: 7183154 | B51: 801-048-2685 | C51: 430691 | D51: 186058 | E51: 3375 | F51: Rogers-Patel | G51: 25391.66 | H51: 30268.76 | I51: 46147 | J51: 46147.368 | K51: 46147.378 | M51: pending | N51: Local | O51: 8939086511 | P51: 2303 | Q51: Invoice | S51: Local Services Ads | T51: running
A52: 5892952 | B52: 801-048-2685 | C52: 100815 | D52: 020727 | E52: 2872 | F52: Dominguez, Rogers and Rice | G52: 44321.01 | H52: 9029.01 | I52: 46148 | J52: 46147.316 | K52: 46147.329 | N52: National | O52: 5341379202 | P52: 2101 | Q52: Invoice | S52: XMO | T52: running
A53: 6312972 | B53: 801-048-2685 | C53: 949463 | D53: 450654 | E53: 9588 | F53: Rodriguez PLC | G53: 22697 | H53: 33255.93 | I53: 46147 | J53: 46147.249 | K53: 46147.249 | M53: pending | N53: National | O53: 0330145251 | P53: 1948 | Q53: Credit Card | S53: Local Services Ads | T53: running
A54: 6312972 | B54: 801-048-2685 | C54: 949463 | D54: 450654 | E54: 9588 | F54: Rodriguez PLC | G54: 2192.62 | H54: 42464.25 | I54: 46147 | J54: 46147.249 | K54: 46147.249 | M54: pending | N54: National | O54: 0330145251 | P54: 1948 | Q54: Credit Card | S54: Local Services Ads | T54: ended | U54: 45097
A55: 2948789 | B55: 801-048-2685 | C55: 616636 | D55: 857341 | E55: 9588 | F55: Olsen-Hart | G55: 29769.91 | H55: 23211.48 | I55: 46147 | J55: 46147.248 | K55: 46147.248 | M55: pending | N55: National | O55: 5153862714 | P55: 2303 | Q55: Credit Card | S55: Local Services Ads | T55: running
A56: 7578384 | B56: 801-048-2685 | C56: 912863 | D56: 289313 | E56: 7636 | F56: Unknown Business | G56: 77827.03 | H56: 34426.92 | I56: 46149 | J56: 46147.248 | K56: 46147.248 | M56: pending | N56: Local | O56: 5457701685 | P56: 1 | Q56: Invoice | S56: Search Engine Marketing | T56: running
A57: 7239407 | B57: 801-048-2685 | C57: 772027 | D57: 171667 | E57: 9980 | F57: Lyons-Wolfe | G57: 41834.62 | H57: 36445.11 | I57: 46147 | J57: 46146.661 | K57: 46147.602 | M57: pending | N57: National | O57: 5500119313 | P57: 2303 | Q57: Credit Card | S57: Local Services Ads | T57: running
A58: 3465599 | B58: 801-048-2685 | C58: 319925 | D58: 832629 | E58: 2816 | F58: Lambert, Hart and Jackson | G58: 57874.69 | H58: 18173.48 | I58: 46147 | J58: 46146.645 | K58: 46146.645 | M58: pending | N58: DummyG | O58: 7497728409 | P58: 2101 | Q58: Invoice | S58: XMO | T58: running
A59: 0581356 | B59: 801-048-2685 | C59: 394906 | D59: 887808 | E59: 2816 | F59: Sanchez-Walters | G59: 78724.67 | H59: 43151.81 | I59: 46147 | J59: 46146.634 | K59: 46146.634 | M59: pending | N59: DummyG | O59: 8229305823 | P59: 2101 | Q59: Invoice | S59: XMO | T59: running
A60: 9167495 | B60: 801-048-2685 | C60: 804492 | D60: 331468 | E60: 2816 | F60: Mitchell, Ross and Higgins | G60: 39555.45 | H60: 5320.64 | I60: 46149 | J60: 46146.614 | K60: 46146.614 | M60: pending | N60: DummyG | O60: 7097270343 | P60: 2101 | Q60: Invoice | S60: XMO | T60: running
A61: 5627006 | B61: 801-048-2685 | C61: 694808 | D61: 447924 | E61: 9980 | F61: Aguirre-Holmes | G61: 10858.23 | H61: 0 | I61: 46150 | J61: 46146.549 | K61: 46146.551 | M61: pending | N61: National | O61: 3711736771 | P61: 2303 | Q61: Credit Card | S61: Local Services Ads | T61: running
A62: 6428523 | B62: 801-048-2685 | C62: 074152 | D62: 174504 | E62: 9980 | F62: Thornton and Sons | G62: 57741.13 | H62: 0 | I62: 46150 | J62: 46146.547 | K62: 46146.548 | M62: pending | N62: National | O62: 0631727954 | P62: 2303 | Q62: Credit Card | S62: Local Services Ads | T62: running
A63: 4292785 | B63: 801-048-2685 | C63: 167310 | D63: 692307 | E63: 9980 | F63: Russell LLC | G63: 75045.23 | H63: 0 | I63: 46150 | J63: 46146.545 | K63: 46146.546 | M63: pending | N63: National | O63: 5996500484 | P63: 2303 | Q63: Credit Card | S63: Local Services Ads | T63: running
A64: 8612462 | B64: 801-048-2685 | C64: 298401 | D64: 038263 | E64: 3698 | F64: Mueller-Brown | G64: 74988.67 | H64: 28980.33 | I64: 46146 | J64: 46146.481 | K64: 46146.481 | M64: pending | N64: National | O64: 3827273902 | P64: 2303 | Q64: Credit Card | S64: Local Services Ads | T64: running
A65: 7936102 | B65: 801-048-2685 | C65: 648266 | D65: 401028 | E65: 8295 | F65: Jimenez-Williams | G65: 13688.2 | H65: 48144.12 | I65: 46147 | J65: 46146.481 | K65: 46146.481 | M65: pending | N65: National | O65: 9802327073 | P65: 2303 | Q65: Credit Card | S65: Local Services Ads | T65: running
A66: 9413283 | B66: 801-048-2685 | C66: 241222 | D66: 316704 | E66: 9226 | F66: Perez PLC | G66: 79300.85 | H66: 5728.59 | I66: 46148 | J66: 46146.481 | K66: 46146.481 | M66: pending | O66: 6644235746 | P66: 2303 | Q66: Invoice | S66: Local Services Ads | T66: running
A67: 6391593 | B67: 801-048-2685 | C67: 472682 | D67: 440493 | E67: 9588 | F67: Barnes Ltd | G67: 33764.49 | H67: 0 | I67: 46147 | J67: 46146.399 | K67: 46146.399 | N67: National | O67: 1060365186 | P67: 2303 | Q67: Credit Card | S67: Local Services Ads | T67: running
A68: 4345910 | B68: 801-048-2685 | C68: 454554 | D68: 726855 | E68: 9932 | F68: Saunders LLC | G68: 62893.69 | H68: 10567.25 | I68: 46147 | J68: 46146.373 | K68: 46146.374 | M68: pending | N68: National | O68: 3996122293 | P68: 2303 | Q68: Credit Card | S68: Local Services Ads | T68: running
A69: 3691955 | B69: 801-048-2685 | C69: 822980 | D69: 444465 | E69: 5673 | F69: Swanson Inc | G69: 62834 | H69: 46359.68 | I69: 46146 | J69: 46146.309 | K69: 46146.311 | M69: pending | N69: National | O69: 1286222605 | P69: 2303 | Q69: Invoice | S69: Local Services Ads | T69: running
A70: 9522373 | B70: 801-048-2685 | C70: 897544 | D70: 348866 | E70: 2872 | F70: Rhodes-Ryan | G70: 63685.83 | H70: 46238.97 | I70: 46146 | J70: 46146.281 | K70: 46146.283 | N70: National | O70: 2845050674 | P70: 2101 | Q70: Invoice | S70: XMO | T70: running
A71: 1945295 | B71: 801-048-2685 | C71: 331071 | D71: 400660 | E71: 2872 | F71: Nelson, Brown and Cook | G71: 38392.97 | H71: 4.27 | I71: 46146 | J71: 46146.28 | K71: 46146.283 | N71: National | O71: 4901951146 | P71: 2101 | Q71: Invoice | S71: XMO | T71: running
A72: 6307088 | B72: 801-048-2685 | C72: 083328 | D72: 206666 | E72: 9588 | F72: Bauer LLC | G72: 29349.57 | H72: 15375.56 | I72: 46147 | J72: 46146.246 | K72: 46146.246 | M72: pending | N72: National | O72: 1543283736 | P72: 1948 | Q72: Credit Card | S72: Local Services Ads | T72: running
A73: 6307088 | B73: 801-048-2685 | C73: 083328 | D73: 206666 | E73: 9588 | F73: Bauer LLC | G73: 39154.96 | H73: 28738.65 | I73: 46147 | J73: 46146.246 | K73: 46146.246 | M73: pending | N73: National | O73: 1543283736 | P73: 1948 | Q73: Credit Card | S73: Local Services Ads | T73: ended | U73: 45098
A74: 7923333 | B74: 801-048-2685 | C74: 441542 | D74: 793091 | E74: 9588 | F74: Hart Ltd | G74: 80459.02 | H74: 7164.32 | I74: 46147 | J74: 46146.246 | K74: 46146.246 | M74: pending | N74: National | O74: 0657546427 | P74: 1948 | Q74: Credit Card | S74: Local Services Ads | T74: running
A75: 7923333 | B75: 801-048-2685 | C75: 441542 | D75: 793091 | E75: 9588 | F75: Hart Ltd | G75: 28069.56 | H75: 30175.85 | I75: 46147 | J75: 46146.246 | K75: 46146.246 | M75: pending | N75: National | O75: 0657546427 | P75: 1948 | Q75: Credit Card | S75: Local Services Ads | T75: ended | U75: 45097
A76: 4979141 | B76: 801-048-2685 | C76: 109475 | D76: 720470 | E76: 9588 | F76: Gilbert Inc | G76: 9880.93 | H76: 0 | I76: 46146 | J76: 46146.245 | K76: 46146.245 | M76: pending | N76: National | O76: 8551880888 | P76: 1948 | Q76: Credit Card | S76: Local Services Ads | T76: running
A77: 4979141 | B77: 801-048-2685 | C77: 109475 | D77: 720470 | E77: 9588 | F77: Gilbert Inc | G77: 14850.52 | H77: 0 | I77: 46146 | J77: 46146.245 | K77: 46146.245 | M77: pending | N77: National | O77: 8551880888 | P77: 1948 | Q77: Credit Card | S77: Local Services Ads | T77: ended | U77: 45092
A78: 7057772 | B78: 801-048-2685 | C78: 239864 | D78: 199556 | E78: 9588 | F78: Sanchez-Walters | G78: 89974.68 | H78: 0 | I78: 46149 | J78: 46146 | K78: 46146.606 | M78: pending | N78: National | O78: 2861392726 | P78: 2303 | Q78: Credit Card | S78: Local Services Ads | T78: running
A79: 3419928 | B79: 801-048-2685 | C79: 275783 | D79: 825699 | E79: 8295 | F79: Mcfarland-Smith | G79: 21483.05 | H79: 56547.9 | I79: 46147 | J79: 46145.481 | K79: 46145.481 | M79: pending | N79: National | O79: 4495317467 | P79: 2303 | Q79: Credit Card | S79: Local Services Ads | T79: running
A80: 5301326 | B80: 801-048-2685 | C80: 213354 | D80: 925703 | E80: 1192 | F80: Mcdowell, Morris and Lopez | G80: 58195.92 | H80: 57171.36 | I80: 46147 | J80: 46145.481 | K80: 46145.481 | M80: pending | N80: National | O80: 0399757415 | P80: 1948 | Q80: Credit Card | S80: Local Services Ads | T80: ended | U80: 45104
A81: 5301326 | B81: 801-048-2685 | C81: 213354 | D81: 925703 | E81: 1192 | F81: Mcdowell, Morris and Lopez | G81: 87517.46 | H81: 4666.28 | I81: 46147 | J81: 46145.481 | K81: 46145.481 | M81: pending | N81: National | O81: 0399757415 | P81: 1948 | Q81: Credit Card | S81: Local Services Ads | T81: running
A82: 8569745 | B82: 801-048-2685 | C82: 574380 | D82: 963626 | E82: 8295 | F82: Brown-Nguyen | G82: 2058.71 | H82: 2697.38 | I82: 46147 | J82: 46145.48 | K82: 46145.48 | M82: pending | N82: National | O82: 5305008933 | P82: 2303 | Q82: Credit Card | S82: Local Services Ads | T82: running
A83: 1442570 | B83: 801-048-2685 | C83: 468311 | D83: 773411 | E83: 8295 | F83: Butler, Thompson and Thomas | G83: 35153.27 | H83: 9663.6 | I83: 46146 | J83: 46145.48 | K83: 46145.48 | M83: pending | N83: National | O83: 0396296713 | P83: 2303 | Q83: Credit Card | S83: Local Services Ads | T83: running
A84: 0284146 | B84: 801-048-2685 | C84: 225854 | D84: 113292 | E84: 1753 | F84: Skinner-Baker | G84: 75782.85 | H84: 12269.74 | I84: 46145 | J84: 46145.239 | K84: 46145.239 | M84: pending | N84: Local | O84: 6547544251 | P84: 2303 | Q84: Credit Card | S84: Local Services Ads | T84: running
A85: 1052353 | B85: 801-048-2685 | C85: 484995 | D85: 261329 | E85: 7521 | F85: Smith-Flores | G85: 50442.38 | H85: 49231.71 | I85: 46145 | J85: 46145.238 | K85: 46145.238 | M85: pending | N85: Local | O85: 9451757439 | P85: 1 | Q85: Invoice | S85: Search Engine Marketing | T85: new
A86: 5856831 | B86: 801-048-2685 | C86: 399170 | D86: 583494 | E86: 8295 | F86: Hoffman, Park and Rios | G86: 32390.76 | H86: 10315.94 | I86: 46147 | J86: 46145 | K86: 46146.626 | M86: pending | N86: National | O86: 9220075859 | P86: 2303 | Q86: Credit Card | S86: Local Services Ads | T86: running
A87: 7681439 | B87: 801-048-2685 | C87: 308844 | D87: 854197 | E87: 8295 | F87: Stewart LLC | G87: 42698.9 | H87: 48247.6 | I87: 46148 | J87: 46145 | K87: 46146.571 | M87: pending | N87: National | O87: 3186894406 | P87: 2303 | Q87: Credit Card | S87: Local Services Ads | T87: running
A88: 5270660 | B88: 801-048-2685 | C88: 209400 | D88: 764159 | E88: 4744 | F88: Collins-Callahan | G88: 99305.84 | H88: 39173.74 | I88: 46147 | J88: 46144.481 | K88: 46144.481 | M88: pending | N88: National | O88: 3751601824 | P88: 2303 | Q88: Credit Card | S88: Local Services Ads | T88: running
A89: 8897963 | B89: 801-048-2685 | C89: 287564 | D89: 033696 | E89: 1192 | F89: Owens-Cole | G89: 68035.73 | H89: 18835.98 | I89: 46147 | J89: 46144.481 | K89: 46144.481 | M89: pending | N89: National | O89: 0986569671 | P89: 2303 | Q89: Credit Card | S89: Local Services Ads | T89: running
A90: 8953837 | B90: 801-048-2685 | C90: 836108 | D90: 582484 | E90: 2539 | F90: Chavez-Carr | G90: 82633.47 | H90: 0 | I90: 46149 | J90: 46144.481 | K90: 46144.481 | M90: pending | N90: National | O90: 7308580035 | P90: 2303 | Q90: Invoice | S90: Local Services Ads | T90: running
A91: 4502089 | B91: 924-255-5564 | C91: 200285 | D91: 025285 | E91: 1192 | F91: Pacheco Ltd | G91: 52278.22 | H91: 0 | I91: 46149 | J91: 46144.481 | K91: 46149.335 | M91: pending | N91: National | O91: 1795628657 | P91: 1948 | Q91: Direct Debit | S91: Local Services Ads | T91: ended | U91: 45097
A92: 4502089 | B92: 924-255-5564 | C92: 200285 | D92: 025285 | E92: 1192 | F92: Pacheco Ltd | G92: 16293.88 | H92: 0 | I92: 46149 | J92: 46144.481 | K92: 46149.335 | M92: pending | N92: National | O92: 1795628657 | P92: 1948 | Q92: Direct Debit | S92: Local Services Ads | T92: running
A93: 7525058 | B93: 924-255-5564 | C93: 444403 | D93: 313635 | E93: 4179 | F93: Rangel, Casey and Berry | G93: 83553.5 | H93: 27134.88 | I93: 46145 | J93: 46144.48 | K93: 46144.48 | M93: pending | N93: DummyG | O93: 1190280732 | P93: 2303 | Q93: Invoice | S93: Local Services Ads | T93: running
A94: 9425858 | B94: 924-255-5564 | C94: 344103 | D94: 876769 | E94: 0501 | F94: Rodriguez and Sons | G94: 98694.32 | H94: 4233.73 | I94: 46147 | J94: 46144.48 | K94: 46144.48 | M94: pending | N94: Local | O94: 8306321628 | P94: 1948 | Q94: Credit Card | S94: Local Services Ads | T94: running
A95: 9425858 | B95: 924-255-5564 | C95: 344103 | D95: 876769 | E95: 0501 | F95: Rodriguez and Sons | G95: 93979 | H95: 27294.8 | I95: 46147 | J95: 46144.48 | K95: 46144.48 | M95: pending | N95: Local | O95: 8306321628 | P95: 1948 | Q95: Credit Card | S95: Local Services Ads | T95: running
A96: 8971327 | B96: 924-255-5564 | C96: 183214 | D96: 178522 | E96: 8295 | F96: Henry Inc | G96: 36677.64 | H96: 56699.75 | I96: 46148 | J96: 46144.48 | K96: 46144.48 | M96: pending | N96: National | O96: 5749547324 | P96: 2303 | Q96: Credit Card | S96: Local Services Ads | T96: running
A97: 5198025 | B97: 924-255-5564 | C97: 712209 | D97: 056522 | E97: 9588 | F97: Phillips, Simpson and Todd | G97: 28582.84 | H97: 26179.43 | I97: 46145 | J97: 46144.48 | K97: 46144.48 | M97: failed | N97: National | O97: 6452215426 | P97: 2303 | Q97: Credit Card | S97: Local Services Ads | T97: running
A98: 5012419 | B98: 924-255-5564 | C98: 126112 | D98: 803717 | E98: 9208 | F98: Bennett-Gonzalez | G98: 37827.68 | H98: 59550.57 | I98: 46147 | J98: 46144.247 | K98: 46144.247 | M98: pending | N98: Local | O98: 1706610954 | P98: 1 | Q98: Credit Card | S98: Search Engine Marketing | T98: running
A99: 1835508 | B99: 924-255-5564 | C99: 858179 | D99: 776210 | E99: 2816 | F99: Anderson-Barron | G99: 89834.39 | H99: 6037.65 | I99: 46147 | J99: 46144.238 | K99: 46144.238 | N99: DummyG | O99: 0835744895 | P99: 2101 | Q99: Invoice | S99: XMO | T99: running
A100: 0445132 | B100: 924-255-5564 | C100: 446372 | D100: 104551 | E100: 9588 | F100: Robinson-Stuart | G100: 53339.66 | H100: 2617.44 | I100: 46146 | J100: 46144.234 | K100: 46146.601 | M100: pending | N100: National | O100: 3732540545 | P100: 2303 | Q100: Credit Card | S100: Local Services Ads | T100: running
A101: 9614812 | B101: 924-255-5564 | C101: 914024 | D101: 978008 | E101: 9588 | F101: Miller Ltd | G101: 94960.12 | H101: 3434.22 | I101: 46147 | J101: 46143.573 | K101: 46146.687 | M101: pending | N101: National | O101: 8036590074 | P101: 1948 | Q101: Credit Card | S101: Local Services Ads | T101: ended | U101: 45114
A102: 9614812 | B102: 924-255-5564 | C102: 914024 | D102: 978008 | E102: 9588 | F102: Miller Ltd | G102: 84179.77 | H102: 49225.17 | I102: 46147 | J102: 46143.573 | K102: 46146.687 | M102: pending | N102: National | O102: 8036590074 | P102: 1948 | Q102: Credit Card | S102: Local Services Ads | T102: running
A103: 3667281 | B103: 924-255-5564 | C103: 940322 | D103: 691689 | E103: 9588 | F103: Peterson, Armstrong and King | G103: 82692.14 | H103: 42444.84 | I103: 46143 | J103: 46143.48 | K103: 46143.48 | M103: pending | N103: National | O103: 4826011890 | P103: 2303 | Q103: Credit Card | S103: Local Services Ads | T103: running
A104: 6752786 | B104: 924-255-5564 | C104: 394221 | D104: 680623 | E104: 9588 | F104: Green, Young and Alvarez | G104: 70121.77 | H104: 59751.31 | I104: 46143 | J104: 46143.48 | K104: 46143.48 | M104: pending | N104: National | O104: 0831190145 | P104: 1948 | Q104: Credit Card | S104: Local Services Ads | T104: running
A105: 6752786 | B105: 924-255-5564 | C105: 394221 | D105: 680623 | E105: 9588 | F105: Green, Young and Alvarez | G105: 76638.46 | H105: 49810.54 | I105: 46143 | J105: 46143.48 | K105: 46143.48 | M105: pending | N105: National | O105: 0831190145 | P105: 1948 | Q105: Credit Card | S105: Local Services Ads | T105: ended | U105: 45585
A106: 1740601 | B106: 924-255-5564 | C106: 083962 | D106: 506760 | E106: 9932 | F106: Grant LLC | G106: 67547.29 | H106: 51274.19 | I106: 46147 | J106: 46143.48 | K106: 46143.48 | N106: National | O106: 3623610581 | P106: 2303 | Q106: Credit Card | S106: Local Services Ads | T106: running
A107: 0285761 | B107: 924-255-5564 | C107: 285764 | D107: 657786 | E107: 3698 | F107: Mcneil Ltd | G107: 94562.79 | H107: 44638.29 | I107: 46143 | J107: 46143.479 | K107: 46143.479 | M107: pending | N107: National | O107: 7088563121 | P107: 2303 | Q107: Credit Card | S107: Local Services Ads | T107: running
...

Sheet MCC data
A1: Account Status | B1: Account name | C1: Account external customer ID | D1: Optimization score | E1: Direct manager name | F1: Direct manager customer ID | G1: Account type | H1: Clicks | I1: Impr. | J1: CTR | K1: Currency code | L1: Avg. CPC | M1: Converted currency code | N1: Avg. CPC (Converted currency) | O1: Cost | P1: Cost (Converted currency) | Q1: Conversions | R1: Conv. rate | S1: Account labels
A2: Active | B2: Anderson, Summers and Jones | C2: 5916500764 | D2: -- | E2: Google LSA Accounts - US | F2: 801-048-2685 | G2: Google Ads | H2: 12372.49 | I2: 1694847 | J2: 0.1556 | K2: USD | L2: 42.89 | M2: USD | N2: 66.56 | O2: 662864 | P2: 748686.95 | Q2: 4767.4 | R2: 0.0939 | S2: --
A3: Active | B3: Thomas and Sons | C3: 1492400035 | D3: -- | E3: Google LSA Accounts - US | F3: 801-048-2685 | G3: Google Ads | H3: 0 | I3: 0 | J3: -- | K3: USD | L3: -- | M3: USD | N3: -- | O3: 0 | P3: -- | Q3: 0 | R3: 0 | S3: --
A4: Active | B4: Martin, Brown and Frank | C4: 2249967510 | D4: -- | E4: Google LSA Accounts - US | F4: 801-048-2685 | G4: Google Ads | H4: 0 | I4: 0 | J4: -- | K4: USD | L4: -- | M4: USD | N4: -- | O4: 0 | P4: -- | Q4: 0 | R4: 0 | S4: --
A5: Active | B5: Hanson, Hall and Case | C5: 5370965818 | D5: -- | E5: Google LSA Accounts - US | F5: 801-048-2685 | G5: Google Ads | H5: 0 | I5: 0 | J5: -- | K5: USD | L5: -- | M5: USD | N5: -- | O5: 0 | P5: -- | Q5: 0 | R5: 0 | S5: --
A6: Active | B6: Coleman, Brown and Brown | C6: 8598321515 | D6: -- | E6: Google LSA Accounts - US | F6: 801-048-2685 | G6: Google Ads | H6: 81502.8 | I6: 1219369.7 | J6: 0.0996 | K6: USD | L6: 16.68 | M6: USD | N6: 139.56 | O6: 0 | P6: 151240.68 | Q6: 3879.58 | R6: 0.1739 | S6: --
A7: Active | B7: Hansen, Murphy and Robinson | C7: 1833846387 | D7: -- | E7: Google LSA Accounts - US | F7: 801-048-2685 | G7: Google Ads | H7: 0 | I7: 0 | J7: -- | K7: USD | L7: -- | M7: USD | N7: -- | O7: 0 | P7: -- | Q7: 0 | R7: 0 | S7: --
A8: Active | B8: Moore, Dawson and Alvarez | C8: 8182903864 | D8: -- | E8: Google LSA Accounts - US | F8: 801-048-2685 | G8: Google Ads | H8: 47851.51 | I8: 997842.38 | J8: 0.0722 | K8: USD | L8: 3.86 | M8: USD | N8: 106.21 | O8: 452811 | P8: 208125.6 | Q8: 496.68 | R8: 0.1617 | S8: --
A9: Active | B9: Reyes and Sons | C9: 1843625072 | D9: -- | E9: Google LSA Accounts - US | F9: 801-048-2685 | G9: Google Ads | H9: 105055.36 | I9: 830622.13 | J9: 0.0857 | K9: USD | L9: 18.45 | M9: USD | N9: 126.32 | O9: - | P9: 230165.96 | Q9: 1669.06 | R9: 0.1375 | S9: Plumbing Utah
A10: Active | B10: Hernandez Group | C10: 4203318384 | D10: -- | E10: Google LSA Accounts - US | F10: 801-048-2685 | G10: Google Ads | H10: 110353.81 | I10: 353037.02 | J10: 0.073 | K10: USD | L10: 0 | M10: USD | N10: 0 | O10: - | P10: 0 | Q10: 0 | R10: 0 | S10: --
A11: Active | B11: Morgan, Leach and Jackson | C11: 1776944144 | D11: -- | E11: Google LSA Accounts - US | F11: 801-048-2685 | G11: Google Ads | H11: 0 | I11: 0 | J11: -- | K11: USD | L11: -- | M11: USD | N11: -- | O11: 0 | P11: -- | Q11: 0 | R11: 0 | S11: --
A12: Active | B12: Serrano-Harrison | C12: 1726373069 | D12: -- | E12: Google LSA Accounts - US | F12: 801-048-2685 | G12: Google Ads | H12: 29816.7 | I12: 1035248.7 | J12: 0.0599 | K12: USD | L12: 36.98 | M12: USD | N12: 96.9 | O12: 0 | P12: 307008.12 | Q12: 346.82 | R12: 0.0631 | S12: --
A13: Active | B13: Perez-Perkins | C13: 1642669667 | D13: -- | E13: Google LSA Accounts - US | F13: 801-048-2685 | G13: Google Ads | H13: 115033.42 | I13: 7022.96 | J13: 0.0782 | K13: USD | L13: 25.72 | M13: USD | N13: 72.68 | O13: 2 | P13: 199235.73 | Q13: 7282.93 | R13: 0.062 | S13: --
A14: Active | B14: Bell and Sons | C14: 9272488948 | D14: -- | E14: Google LSA Accounts - US | F14: 801-048-2685 | G14: Google Ads | H14: 0 | I14: 0 | J14: -- | K14: USD | L14: -- | M14: USD | N14: -- | O14: 0 | P14: -- | Q14: 0 | R14: 0 | S14: --
A15: Active | B15: Perez PLC | C15: 8604361768 | D15: -- | E15: Google LSA Accounts - US | F15: 801-048-2685 | G15: Google Ads | H15: 114222.92 | I15: 80397.87 | J15: 0.0689 | K15: USD | L15: 13.34 | M15: USD | N15: 145.59 | O15: 669940 | P15: 519744.53 | Q15: 11718.28 | R15: 0.237 | S15: --
A16: Active | B16: Walton-White | C16: 6090633975 | D16: -- | E16: Google LSA Accounts - US | F16: 801-048-2685 | G16: Google Ads | H16: 0 | I16: 0 | J16: -- | K16: USD | L16: -- | M16: USD | N16: -- | O16: 0 | P16: -- | Q16: 0 | R16: 0 | S16: --
A17: Active | B17: Riley-Allen | C17: 8880158481 | D17: -- | E17: Google LSA Accounts - US | F17: 801-048-2685 | G17: Google Ads | H17: 131523.93 | I17: 145239.12 | J17: 0.1894 | K17: USD | L17: 18.67 | M17: USD | N17: 71.06 | O17: 589183 | P17: 377490.59 | Q17: 2073.41 | R17: 0.0262 | S17: --
A18: Active | B18: Gomez-Barker | C18: 2917330873 | D18: -- | E18: Google LSA Accounts - US | F18: 801-048-2685 | G18: Google Ads | H18: 133027.9 | I18: 116662.78 | J18: 0.1098 | K18: USD | L18: 5.92 | M18: USD | N18: 65.86 | O18: 560745 | P18: 667631.88 | Q18: 4471.68 | R18: 0.1583 | S18: Allen HVAC
A19: Active | B19: Sanchez-Walters | C19: 3561265250 | D19: -- | E19: Google LSA Accounts - US | F19: 801-048-2685 | G19: Google Ads | H19: 102873.33 | I19: 378675.83 | J19: 0.0235 | K19: USD | L19: 39.09 | M19: USD | N19: 145.35 | O19: 784833 | P19: 601240.66 | Q19: 7142.47 | R19: 0.1765 | S19: --
A20: Active | B20: Chang, Gardner and Davis | C20: 5531215398 | D20: -- | E20: Google LSA Accounts - US | F20: 801-048-2685 | G20: Google Ads | H20: 0 | I20: 0 | J20: -- | K20: USD | L20: -- | M20: USD | N20: -- | O20: 0 | P20: -- | Q20: 0 | R20: 0 | S20: --
A21: Active | B21: Garrison, Garner and Mitchell | C21: 5753787783 | D21: -- | E21: Google LSA Accounts - US | F21: 801-048-2685 | G21: Google Ads | H21: 0 | I21: 0 | J21: -- | K21: USD | L21: -- | M21: USD | N21: -- | O21: 0 | P21: -- | Q21: 0 | R21: 0 | S21: --
A22: Active | B22: Hernandez, Adams and Roberts | C22: 3053963118 | D22: -- | E22: Google LSA Accounts - US | F22: 801-048-2685 | G22: Google Ads | H22: 0 | I22: 0 | J22: -- | K22: USD | L22: -- | M22: USD | N22: -- | O22: 0 | P22: -- | Q22: 0 | R22: 0 | S22: --
A23: Active | B23: Newton-Flores | C23: 6045301447 | D23: -- | E23: Google LSA Accounts - US | F23: 801-048-2685 | G23: Google Ads | H23: 7493.15 | I23: 334162.35 | J23: 0.1292 | K23: USD | L23: 39.78 | M23: USD | N23: 63.46 | O23: 30534 | P23: 131652.89 | Q23: 8824.15 | R23: 0.1463 | S23: HVAC Utah
A24: Active | B24: Mcdaniel, Carlson and Stein | C24: 9729452134 | D24: -- | E24: Google LSA Accounts - US | F24: 801-048-2685 | G24: Google Ads | H24: 48731.73 | I24: 1687513 | J24: 0.0771 | K24: USD | L24: 7.02 | M24: USD | N24: 79.13 | O24: 196759 | P24: 552838.18 | Q24: 5448.78 | R24: 0.1123 | S24: --
A25: Active | B25: Schneider PLC | C25: 0690984218 | D25: -- | E25: Google LSA Accounts - US | F25: 801-048-2685 | G25: Google Ads | H25: 85228.81 | I25: 1020698.7 | J25: 0.1396 | K25: USD | L25: 29.9 | M25: USD | N25: 125.43 | O25: 320064 | P25: 383857.78 | Q25: 2531.61 | R25: 0.1126 | S25: HVAC Washington
A26: Active | B26: Tucker-Wilson | C26: 0051367125 | D26: -- | E26: Google LSA Accounts - US | F26: 801-048-2685 | G26: Google Ads | H26: 0 | I26: 0 | J26: -- | K26: USD | L26: -- | M26: USD | N26: -- | O26: 0 | P26: -- | Q26: 0 | R26: 0 | S26: --
A27: Active | B27: Steele PLC | C27: 8498634123 | D27: -- | E27: Google LSA Accounts - US | F27: 801-048-2685 | G27: Google Ads | H27: 0 | I27: 1461987.7 | J27: 0 | K27: USD | L27: -- | M27: USD | N27: -- | O27: 0 | P27: 0 | Q27: 0 | R27: 0 | S27: --
A28: Active | B28: Clarke PLC | C28: 3277829980 | D28: -- | E28: Google LSA Accounts - US | F28: 801-048-2685 | G28: Google Ads | H28: 0 | I28: 0 | J28: -- | K28: USD | L28: -- | M28: USD | N28: -- | O28: 0 | P28: -- | Q28: 0 | R28: 0 | S28: --
A29: Active | B29: Hunt PLC | C29: 3940476622 | D29: -- | E29: Google LSA Accounts - US | F29: 801-048-2685 | G29: Google Ads | H29: 0 | I29: 0 | J29: -- | K29: USD | L29: -- | M29: USD | N29: -- | O29: 0 | P29: -- | Q29: 0 | R29: 0 | S29: --
A30: Active | B30: Jones Group | C30: 7774057945 | D30: -- | E30: Google LSA Accounts - US | F30: 801-048-2685 | G30: Google Ads | H30: 0 | I30: 0 | J30: -- | K30: USD | L30: -- | M30: USD | N30: -- | O30: 0 | P30: -- | Q30: 0 | R30: 0 | S30: --
A31: Active | B31: Johnson-Mckenzie | C31: 8318921616 | D31: -- | E31: Google LSA Accounts - US | F31: 801-048-2685 | G31: Google Ads | H31: 102125.79 | I31: 1391408.4 | J31: 0.1393 | K31: USD | L31: 37.81 | M31: USD | N31: 131.01 | O31: 100115 | P31: 825591.48 | Q31: 2574.51 | R31: 0.1715 | S31: --
A32: Active | B32: Browning, Brown and Pearson | C32: 6833184923 | D32: -- | E32: Google LSA Accounts - US | F32: 801-048-2685 | G32: Google Ads | H32: 1745.09 | I32: 829167.54 | J32: 0.09 | K32: USD | L32: 0 | M32: USD | N32: 0 | O32: 0 | P32: 0 | Q32: 0 | R32: 0 | S32: --
A33: Active | B33: Hughes, Blair and Gates | C33: 2261405045 | D33: -- | E33: Google LSA Accounts - US | F33: 801-048-2685 | G33: Google Ads | H33: 306.16 | I33: 297523.26 | J33: 0.112 | K33: USD | L33: 22.2 | M33: USD | N33: 158.35 | O33: 137868 | P33: 822772.45 | Q33: 1675.99 | R33: 0.0056 | S33: --
A34: Active | B34: Ramos and Sons | C34: 1057098735 | D34: -- | E34: Google LSA Accounts - US | F34: 801-048-2685 | G34: Google Ads | H34: 0 | I34: 0 | J34: -- | K34: USD | L34: -- | M34: USD | N34: -- | O34: 0 | P34: -- | Q34: 0 | R34: 0 | S34: --
A35: Active | B35: Kelley, Smith and Roberson | C35: 1270695837 | D35: -- | E35: Google LSA Accounts - US | F35: 801-048-2685 | G35: Google Ads | H35: 0 | I35: 0 | J35: -- | K35: USD | L35: -- | M35: USD | N35: -- | O35: 0 | P35: -- | Q35: 0 | R35: 0 | S35: --
A36: Active | B36: Lopez-Vasquez | C36: 5550975527 | D36: -- | E36: Google LSA Accounts - US | F36: 801-048-2685 | G36: Google Ads | H36: 0 | I36: 0 | J36: -- | K36: USD | L36: -- | M36: USD | N36: -- | O36: 0 | P36: -- | Q36: 0 | R36: 0 | S36: --
A37: Active | B37: Russell, Patel and Cox | C37: 1667099462 | D37: -- | E37: Google LSA Accounts - US | F37: 801-048-2685 | G37: Google Ads | H37: 12385.3 | I37: 1612667.4 | J37: 0.0525 | K37: USD | L37: 21.13 | M37: USD | N37: 59.04 | O37: 635728 | P37: 419024.18 | Q37: 8736.84 | R37: 0.045 | S37: --
A38: Active | B38: Vazquez PLC | C38: 8284447121 | D38: -- | E38: Google LSA Accounts - US | F38: 801-048-2685 | G38: Google Ads | H38: 81532.21 | I38: 862475.37 | J38: 0.0915 | K38: USD | L38: 10.65 | M38: USD | N38: 13.16 | O38: 43002 | P38: 799188.15 | Q38: 4434.82 | R38: 0.1329 | S38: --
A39: Active | B39: Santiago Inc | C39: 6834399267 | D39: -- | E39: Google LSA Accounts - US | F39: 801-048-2685 | G39: Google Ads | H39: 0 | I39: 0 | J39: -- | K39: USD | L39: -- | M39: USD | N39: -- | O39: 0 | P39: -- | Q39: 0 | R39: 0 | S39: --
A40: Active | B40: Barrera Inc | C40: 0866982738 | D40: -- | E40: Google LSA Accounts - US | F40: 801-048-2685 | G40: Google Ads | H40: 0 | I40: 0 | J40: -- | K40: USD | L40: -- | M40: USD | N40: -- | O40: 0 | P40: -- | Q40: 0 | R40: 0 | S40: --
A41: Active | B41: Petersen LLC | C41: 5234973813 | D41: -- | E41: Google LSA Accounts - US | F41: 801-048-2685 | G41: Google Ads | H41: 5371.26 | I41: 1704735 | J41: 0.0372 | K41: USD | L41: 21.92 | M41: USD | N41: 35.19 | O41: 361780 | P41: 711361.85 | Q41: 11920.2 | R41: 0.122 | S41: --
A42: Active | B42: Carpenter-Mccullough | C42: 1746575984 | D42: -- | E42: Google LSA Accounts - US | F42: 801-048-2685 | G42: Google Ads | H42: 121468.28 | I42: 1695676.5 | J42: 0.2112 | K42: USD | L42: 42.19 | M42: USD | N42: 100.32 | O42: 38447 | P42: 515680.9 | Q42: 1451.32 | R42: 0.0565 | S42: --
A43: Active | B43: Rogers-Patel | C43: 8939086511 | D43: -- | E43: Google LSA Accounts - US | F43: 801-048-2685 | G43: Google Ads | H43: 0 | I43: 0 | J43: -- | K43: USD | L43: -- | M43: USD | N43: -- | O43: 0 | P43: -- | Q43: 0 | R43: 0 | S43: --
A44: Active | B44: Dominguez, Rogers and Rice | C44: 5341379202 | D44: -- | E44: Google LSA Accounts - US | F44: 801-048-2685 | G44: Google Ads | H44: 102915.89 | I44: 1633954.3 | J44: 0.0578 | K44: USD | L44: 24.56 | M44: USD | N44: 155.29 | O44: 396778 | P44: 432404.5 | Q44: 14694.72 | R44: 0.0325 | S44: --
A45: Active | B45: Rodriguez PLC | C45: 0330145251 | D45: -- | E45: Google LSA Accounts - US | F45: 801-048-2685 | G45: Google Ads | H45: 0 | I45: 513189.89 | J45: 0 | K45: USD | L45: -- | M45: USD | N45: -- | O45: 0 | P45: 0 | Q45: 0 | R45: 0 | S45: --
A46: Active | B46: Olsen-Hart | C46: 5153862714 | D46: -- | E46: Google LSA Accounts - US | F46: 801-048-2685 | G46: Google Ads | H46: 0 | I46: 0 | J46: -- | K46: USD | L46: -- | M46: USD | N46: -- | O46: 0 | P46: -- | Q46: 0 | R46: 0 | S46: --
A47: Active | C47: 5457701685 | D47: -- | E47: Google LSA Accounts - US | F47: 801-048-2685 | G47: Google Ads | H47: 0 | I47: 0 | J47: -- | K47: USD | L47: -- | M47: USD | N47: -- | O47: 0 | P47: -- | Q47: 0 | R47: 0 | S47: --
A48: Active | B48: Lyons-Wolfe | C48: 5500119313 | D48: -- | E48: Google LSA Accounts - US | F48: 801-048-2685 | G48: Google Ads | H48: 111667.15 | I48: 319953.09 | J48: 0.1051 | K48: USD | L48: 24.58 | M48: USD | N48: 130.25 | O48: 3029 | P48: 675388.67 | Q48: 3021.45 | R48: 0.1071 | S48: --
A49: Active | B49: Lambert, Hart and Jackson | C49: 7497728409 | D49: -- | E49: Google LSA Accounts - US | F49: 801-048-2685 | G49: Google Ads | H49: 0 | I49: 0 | J49: -- | K49: USD | L49: -- | M49: USD | N49: -- | O49: 0 | P49: -- | Q49: 0 | R49: 0 | S49: --
A50: Active | B50: Sanchez-Walters | C50: 8229305823 | D50: -- | E50: Google LSA Accounts - US | F50: 801-048-2685 | G50: Google Ads | H50: 13321.59 | I50: 440022.49 | J50: 0.0387 | K50: USD | L50: 21.7 | M50: USD | N50: 10.91 | O50: 480635 | P50: 225804.54 | Q50: 1252.95 | R50: 0.0227 | S50: --
A51: Active | B51: Mitchell, Ross and Higgins | C51: 7097270343 | D51: -- | E51: Google LSA Accounts - US | F51: 801-048-2685 | G51: Google Ads | H51: 0 | I51: 0 | J51: -- | K51: USD | L51: -- | M51: USD | N51: -- | O51: 0 | P51: -- | Q51: 0 | R51: 0 | S51: --
A52: Active | B52: Aguirre-Holmes | C52: 3711736771 | D52: -- | E52: Google LSA Accounts - US | F52: 801-048-2685 | G52: Google Ads | H52: 0 | I52: 0 | J52: -- | K52: USD | L52: -- | M52: USD | N52: -- | O52: 0 | P52: -- | Q52: 0 | R52: 0 | S52: --
A53: Active | B53: Thornton and Sons | C53: 0631727954 | D53: -- | E53: Google LSA Accounts - US | F53: 801-048-2685 | G53: Google Ads | H53: 933.41 | I53: 1334558.6 | J53: 0.1035 | K53: USD | L53: 29.87 | M53: USD | N53: 112.81 | O53: 374301 | P53: 505297.42 | Q53: 14712.62 | R53: 0.0892 | S53: --
A54: Active | B54: Russell LLC | C54: 5996500484 | D54: -- | E54: Google LSA Accounts - US | F54: 801-048-2685 | G54: Google Ads | H54: 0 | I54: 0 | J54: -- | K54: USD | L54: -- | M54: USD | N54: -- | O54: 0 | P54: -- | Q54: 0 | R54: 0 | S54: --
A55: Active | B55: Mueller-Brown | C55: 3827273902 | D55: -- | E55: Google LSA Accounts - US | F55: 801-048-2685 | G55: Google Ads | H55: 0 | I55: 0 | J55: -- | K55: USD | L55: -- | M55: USD | N55: -- | O55: 0 | P55: -- | Q55: 0 | R55: 0 | S55: --
A56: Active | B56: Jimenez-Williams | C56: 9802327073 | D56: -- | E56: Google LSA Accounts - US | F56: 801-048-2685 | G56: Google Ads | H56: 82270.28 | I56: 1698088.6 | J56: 0.128 | K56: USD | L56: 40.31 | M56: USD | N56: 50.98 | O56: 592952 | P56: 327941.92 | Q56: 11889.11 | R56: 0.1345 | S56: Allen Plum & Electric
A57: Active | B57: Perez PLC | C57: 6644235746 | D57: -- | E57: Google LSA Accounts - US | F57: 801-048-2685 | G57: Google Ads | H57: 114008.44 | I57: 531190.89 | J57: 0.0874 | K57: USD | L57: 27.01 | M57: USD | N57: 41.57 | O57: 240923 | P57: 814819.73 | Q57: 1380.76 | R57: 0.0816 | S57: --
A58: Active | B58: Barnes Ltd | C58: 1060365186 | D58: -- | E58: Google LSA Accounts - US | F58: 801-048-2685 | G58: Google Ads | H58: 0 | I58: 0 | J58: -- | K58: USD | L58: -- | M58: USD | N58: -- | O58: 0 | P58: -- | Q58: 0 | R58: 0 | S58: --
A59: Active | B59: Saunders LLC | C59: 3996122293 | D59: -- | E59: Google LSA Accounts - US | F59: 801-048-2685 | G59: Google Ads | H59: 0 | I59: 0 | J59: -- | K59: USD | L59: -- | M59: USD | N59: -- | O59: 0 | P59: -- | Q59: 0 | R59: 0 | S59: --
A60: Active | B60: Swanson Inc | C60: 1286222605 | D60: -- | E60: Google LSA Accounts - US | F60: 801-048-2685 | G60: Google Ads | H60: 69916.91 | I60: 421368.29 | J60: 0.0726 | K60: USD | L60: 14.85 | M60: USD | N60: 50.23 | O60: 107090 | P60: 4015.83 | Q60: 14640.98 | R60: 0.0396 | S60: --
A61: Active | B61: Rhodes-Ryan | C61: 2845050674 | D61: -- | E61: Google LSA Accounts - US | F61: 801-048-2685 | G61: Google Ads | H61: 119681.35 | I61: 975822.65 | J61: 0.0929 | K61: USD | L61: 24.81 | M61: USD | N61: 21.29 | O61: 31642 | P61: 728056.68 | Q61: 8262.6 | R61: 0.1327 | S61: --
A62: Active | B62: Nelson, Brown and Cook | C62: 4901951146 | D62: -- | E62: Google LSA Accounts - US | F62: 801-048-2685 | G62: Google Ads | H62: 0 | I62: 0 | J62: -- | K62: USD | L62: -- | M62: USD | N62: -- | O62: 0 | P62: -- | Q62: 0 | R62: 0 | S62: --
A63: Active | B63: Bauer LLC | C63: 1543283736 | D63: -- | E63: Google LSA Accounts - US | F63: 801-048-2685 | G63: Google Ads | H63: 0 | I63: 0 | J63: -- | K63: USD | L63: -- | M63: USD | N63: -- | O63: 0 | P63: -- | Q63: 0 | R63: 0 | S63: --
A64: Active | B64: Hart Ltd | C64: 0657546427 | D64: -- | E64: Google LSA Accounts - US | F64: 801-048-2685 | G64: Google Ads | H64: 0 | I64: 0 | J64: -- | K64: USD | L64: -- | M64: USD | N64: -- | O64: 0 | P64: -- | Q64: 0 | R64: 0 | S64: --
A65: Active | B65: Gilbert Inc | C65: 8551880888 | D65: -- | E65: Google LSA Accounts - US | F65: 801-048-2685 | G65: Google Ads | H65: 0 | I65: 0 | J65: -- | K65: USD | L65: -- | M65: USD | N65: -- | O65: 0 | P65: -- | Q65: 0 | R65: 0 | S65: --
A66: Active | B66: Sanchez-Walters | C66: 2861392726 | D66: -- | E66: Google LSA Accounts - US | F66: 801-048-2685 | G66: Google Ads | H66: 25776.05 | I66: 423672.18 | J66: 0.0375 | K66: USD | L66: 19.05 | M66: USD | N66: 137.26 | O66: 644997 | P66: 399990.9 | Q66: 12167.81 | R66: 0.0638 | S66: --
A67: Active | B67: Mcfarland-Smith | C67: 4495317467 | D67: -- | E67: Google LSA Accounts - US | F67: 801-048-2685 | G67: Google Ads | H67: 0 | I67: 0 | J67: -- | K67: USD | L67: -- | M67: USD | N67: -- | O67: 0 | P67: -- | Q67: 0 | R67: 0 | S67: --
A68: Active | B68: Mcdowell, Morris and Lopez | C68: 0399757415 | D68: -- | E68: Google LSA Accounts - US | F68: 801-048-2685 | G68: Google Ads | H68: 50453.38 | I68: 1656177.2 | J68: 0.0432 | K68: USD | L68: 7.61 | M68: USD | N68: 86.22 | O68: 387634 | P68: 821057.96 | Q68: 10022.1 | R68: 0.0825 | S68: --
A69: Active | B69: Brown-Nguyen | C69: 5305008933 | D69: -- | E69: Google LSA Accounts - US | F69: 801-048-2685 | G69: Google Ads | H69: 0 | I69: 0 | J69: -- | K69: USD | L69: -- | M69: USD | N69: -- | O69: 0 | P69: -- | Q69: 0 | R69: 0 | S69: --
A70: Active | B70: Butler, Thompson and Thomas | C70: 0396296713 | D70: -- | E70: Google LSA Accounts - US | F70: 801-048-2685 | G70: Google Ads | H70: 14011.28 | I70: 576014.93 | J70: 0.0854 | K70: USD | L70: 19.92 | M70: USD | N70: 101.56 | O70: 436714 | P70: 672412.2 | Q70: 14308.47 | R70: 0.1378 | S70: --
A71: Active | B71: Skinner-Baker | C71: 6547544251 | D71: -- | E71: Google LSA Accounts - US | F71: 801-048-2685 | G71: Google Ads | H71: 62015.06 | I71: 1541619.1 | J71: 0.0931 | K71: USD | L71: 22.59 | M71: USD | N71: 21.62 | O71: 641209 | P71: 529481.89 | Q71: 9925.32 | R71: 0.132 | S71: --
A72: Active | B72: Smith-Flores | C72: 9451757439 | D72: -- | E72: Google LSA Accounts - US | F72: 801-048-2685 | G72: Google Ads | H72: 0 | I72: 0 | J72: -- | K72: CAD | L72: -- | M72: USD | N72: -- | O72: 0 | P72: -- | Q72: 0 | R72: 0 | S72: --
A73: Active | B73: Hoffman, Park and Rios | C73: 9220075859 | D73: -- | E73: Google LSA Accounts - US | F73: 801-048-2685 | G73: Google Ads | H73: 57164.71 | I73: 1349434.2 | J73: 0.0451 | K73: USD | L73: 2.76 | M73: USD | N73: 154.12 | O73: 141487 | P73: 491229.5 | Q73: 6227.71 | R73: 0.0345 | S73: --
A74: Active | B74: Stewart LLC | C74: 3186894406 | D74: -- | E74: Google LSA Accounts - US | F74: 801-048-2685 | G74: Google Ads | H74: 5068.45 | I74: 1018920.3 | J74: 0.115 | K74: USD | L74: 27.4 | M74: USD | N74: 119.71 | O74: 225456 | P74: 81979.63 | Q74: 13075.27 | R74: 0.102 | S74: --
A75: Active | B75: Collins-Callahan | C75: 3751601824 | D75: -- | E75: Google LSA Accounts - US | F75: 801-048-2685 | G75: Google Ads | H75: 52414.54 | I75: 240553.39 | J75: 0.0589 | K75: USD | L75: 21.87 | M75: USD | N75: 73.33 | O75: 826461 | P75: 129714.51 | Q75: 9763.32 | R75: 0.0372 | S75: --
A76: Active | B76: Owens-Cole | C76: 0986569671 | D76: -- | E76: Google LSA Accounts - US | F76: 801-048-2685 | G76: Google Ads | H76: 0 | I76: 0 | J76: -- | K76: USD | L76: -- | M76: USD | N76: -- | O76: 0 | P76: -- | Q76: 0 | R76: 0 | S76: --
A77: Active | B77: Chavez-Carr | C77: 7308580035 | D77: -- | E77: Google LSA Accounts - US | F77: 801-048-2685 | G77: Google Ads | H77: 131207.23 | I77: 915816.14 | J77: 0.152 | K77: USD | L77: 38.43 | M77: USD | N77: 46.08 | O77: 755936 | P77: 344896.58 | Q77: 2606.66 | R77: 0.1262 | S77: --
A78: Active | B78: Pacheco Ltd | C78: 1795628657 | D78: -- | E78: National Brands LSA | F78: 924-255-5564 | G78: Google Ads | H78: 110928.03 | I78: 1623987.3 | J78: 0.1626 | K78: USD | L78: 38.65 | M78: 614.17 | N78: 32.57 | O78: 632957 | P78: --
A79: Active | B79: Rangel, Casey and Berry | C79: 1190280732 | D79: -- | E79: National Brands LSA | F79: 924-255-5564 | G79: Google Ads | H79: 94169.46 | I79: 663943.2 | J79: 0.043 | K79: USD | L79: 4.86 | M79: 681.17 | N79: 23.22 | O79: 314322 | P79: --
A80: Active | B80: Rodriguez and Sons | C80: 8306321628 | D80: -- | E80: National Brands LSA | F80: 924-255-5564 | G80: Google Ads | H80: 45293.55 | I80: 1579350.8 | J80: 0.1349 | K80: USD | L80: 27.76 | M80: 78.1 | N80: 152.25 | O80: 40973 | P80: 56643.91
A81: Active | B81: Henry Inc | C81: 5749547324 | D81: -- | E81: National Brands LSA | F81: 924-255-5564 | G81: Google Ads | H81: 0 | I81: 0 | J81: -- | K81: USD | L81: -- | M81: 0 | N81: 0 | O81: 0 | P81: --
A82: Active | B82: Phillips, Simpson and Todd | C82: 6452215426 | D82: -- | E82: National Brands LSA | F82: 924-255-5564 | G82: Google Ads | H82: 0 | I82: 0 | J82: -- | K82: USD | L82: -- | M82: 0 | N82: 0 | O82: 0 | P82: 207239.07
A83: Active | B83: Bennett-Gonzalez | C83: 1706610954 | D83: -- | E83: National Brands LSA | F83: 924-255-5564 | G83: Google Ads | H83: 59925.86 | I83: 999934.59 | J83: 0.1366 | K83: USD | L83: 28.18 | M83: 854.2 | N83: 46.17 | O83: 205595 | P83: 843565.67
A84: Active | B84: Anderson-Barron | C84: 0835744895 | D84: -- | E84: National Brands LSA | F84: 924-255-5564 | G84: Google Ads | H84: 93249.11 | I84: 388371.12 | J84: 0.0995 | K84: USD | L84: 44.4 | M84: 1294.23 | N84: 132.43 | O84: 445619 | P84: 628529.45
A85: Active | B85: Robinson-Stuart | C85: 3732540545 | D85: -- | E85: National Brands LSA | F85: 924-255-5564 | G85: Google Ads | H85: 0 | I85: 0 | J85: -- | K85: USD | L85: -- | M85: 0 | N85: 0 | O85: 0 | P85: 271633.23
A86: Active | B86: Miller Ltd | C86: 8036590074 | D86: -- | E86: National Brands LSA | F86: 924-255-5564 | G86: Google Ads | H86: 70658.77 | I86: 1287844 | J86: 0.1796 | K86: USD | L86: 22.81 | M86: 803.65 | N86: 139.27 | O86: 806168 | P86: 464794.88
A87: Active | B87: Peterson, Armstrong and King | C87: 4826011890 | D87: -- | E87: National Brands LSA | F87: 924-255-5564 | G87: Google Ads | H87: 0 | I87: 0 | J87: -- | K87: USD | L87: -- | M87: 0 | N87: 0 | O87: 0 | P87: 256304.57
A88: Active | B88: Green, Young and Alvarez | C88: 0831190145 | D88: -- | E88: National Brands LSA | F88: 924-255-5564 | G88: Google Ads | H88: 0 | I88: 0 | J88: -- | K88: USD | L88: -- | M88: 0 | N88: 0 | O88: 0 | P88: --
A89: Active | B89: Grant LLC | C89: 3623610581 | D89: -- | E89: National Brands LSA | F89: 924-255-5564 | G89: Google Ads | H89: 66439.93 | I89: 757124.62 | J89: 0.1459 | K89: USD | L89: 14.63 | M89: 1164.02 | N89: 49.09 | O89: 638961 | P89: 336051.15
A90: Active | B90: Mcneil Ltd | C90: 7088563121 | D90: -- | E90: National Brands LSA | F90: 924-255-5564 | G90: Google Ads | H90: 15626.99 | I90: 296532.83 | J90: 0.1552 | K90: USD | L90: 10.33 | M90: 1185.06 | N90: 79.97 | O90: 499849 | P90: 620364.07
A91: Active | B91: Mann, Ellis and Fields | C91: 7230454006 | D91: -- | E91: National Brands LSA | F91: 924-255-5564 | G91: Google Ads | H91: 89383.05 | I91: 885116.96 | J91: 0.0986 | K91: USD | L91: 43.74 | M91: 2461.68 | N91: 114.57 | O91: 536665 | P91: 490111.69
A92: Active | B92: Simmons, Kelley and Hahn | C92: 7985267438 | D92: -- | E92: National Brands LSA | F92: 924-255-5564 | G92: Google Ads | H92: 110829.41 | I92: 774536.35 | J92: 0.1585 | K92: USD | L92: 42.22 | M92: 728.6 | N92: 38.36 | O92: 327784 | P92: --
A93: Active | B93: Martin-Cervantes | C93: 5680884355 | D93: -- | E93: National Brands LSA | F93: 924-255-5564 | G93: Google Ads | H93: 116392.82 | I93: 258058.82 | J93: 0.1075 | K93: USD | L93: 11.66 | M93: 637.66 | N93: 64.31 | O93: 410872 | P93: --
A94: Active | B94: Mitchell, Knight and Hughes | C94: 6141767314 | D94: -- | E94: National Brands LSA | F94: 924-255-5564 | G94: Google Ads | H94: 0 | I94: 0 | J94: -- | K94: USD | L94: -- | M94: 0 | N94: 0 | O94: 0 | P94: 372848.02
A95: Active | B95: Franco and Sons | C95: 7314968304 | D95: -- | E95: National Brands LSA | F95: 924-255-5564 | G95: Google Ads | H95: 0 | I95: 0 | J95: -- | K95: USD | L95: -- | M95: 0 | N95: 0 | O95: 0 | P95: --
A96: Active | B96: Mayer LLC | C96: 0471863085 | D96: -- | E96: National Brands LSA | F96: 924-255-5564 | G96: Google Ads | H96: 70765.54 | I96: 1434863 | J96: 0.2 | K96: USD | L96: 0 | M96: 0 | N96: 0 | O96: 0 | P96: --
A97: Active | B97: Powell-Patterson | C97: 4173282089 | D97: -- | E97: National Brands LSA | F97: 924-255-5564 | G97: Google Ads | H97: 0 | I97: 0 | J97: -- | K97: USD | L97: -- | M97: 0 | N97: 0 | O97: 0 | P97: --
A98: Active | B98: Crawford-Simon | C98: 7901483298 | D98: -- | E98: National Brands LSA | F98: 924-255-5564 | G98: Google Ads | H98: 0 | I98: 0 | J98: -- | K98: USD | L98: -- | M98: 0 | N98: 0 | O98: 1 | P98: --
A99: Active | B99: Long and Sons | C99: 3612215844 | D99: -- | E99: National Brands LSA | F99: 924-255-5564 | G99: Google Ads | H99: 12310.41 | I99: 1409365 | J99: 0.1589 | K99: USD | L99: 30.64 | M99: 661.2 | N99: 54.63 | O99: 250967 | P99: --
A100: Active | B100: Butler-Mitchell | C100: 7759843909 | D100: -- | E100: National Brands LSA | F100: 924-255-5564 | G100: Google Ads | H100: 104099.49 | I100: 583834.66 | J100: 0.1023 | K100: USD | L100: 0 | M100: 0 | N100: 0 | O100: 0 | P100: 404025.3
...
